Workbook

Sheet Cover
A1: IKEA Egypt · Multi-Source Paid Media & UTM Planning System
A2: DEPI 2026 Graduation Project #5 · TEAM 1 · Offer: New Home Starter Bundle
A5: Project brief
A6: Brand | B6: IKEA Egypt (Al-Futtaim franchise, 3 stores, room planner, IKEA Family, click-and-collect)
A7: Target | B7: Mariam Adel: first-time furnisher, compound couples in New Cairo and 6th of October. Gehaz families excluded.
A8: Goal | B8: Sell the New Home Starter Bundle profitably across 7 paid sources + CRM in a 30-day test, then reallocate budget from evidence.
A9: Scope | B9: Funnel objectives, audience stages, budget split, UTM convention, tracking plan, attribution comparison, simulated-data optimization.
A10: North star + 4 | B10: North star: revenue after ad spend at margin. Supporting: CTR (traffic), CVR (conversion), CPA (cost), ROAS (value).
A11: Headline results (live)
A12: Test-month spend (EGP) | B12: =Dashboard!A5 -> 249997
A13: Test-month revenue (EGP) | B13: =Dashboard!B5 -> 1027510
A14: Blended ROAS vs target | B14: =TEXT(Dashboard!D5,"0.00")&"x vs "&TEXT(Inputs!$B$10,"0.0")&"x" -> 4.11x vs 3.5x
A15: Projected ROAS after reallocation | B15: =Optimization!E28 -> 4.7933879
A16: Projected extra revenue next month (EGP) | B16: =Optimization!E29 -> 163514.18
A18: How the sheets connect
A19: Inputs | B19: Budget, AOV, margin, targets, thresholds. Change here, everything updates.
A20: Funnel & Audiences | B20: Who we reach at each stage, with what message and which offer.
A21: Audience & Retargeting | B21: Cold / warm / hot / customer tiers, windows, exclusions, frequency, retargeting sequence.
A22: Media Plan | B22: 8 campaigns: platform, stage, tier, budget, benchmarks, forecast, learning objective per line.
A23: Budget Split | B23: Stage / tier / platform / weekly views of the plan.
A24: Creative Testing | B24: Offer ladder, 9 copy-led ad concepts, 6 one-variable creative tests with decision rules.
A25: UTM Builder | B25: Naming convention + auto-built tracked URLs for every campaign.
A26: Tracking Plan | B26: GA4 events, GTM triggers, pixel mapping, launch QA checklist.
A27: Attribution | B27: Same 12 journeys under last click, first click, linear, position-based.
A28: Sample Data | B28: Simulated daily export for the test month (240 rows).
A29: Dashboard | B29: Scorecard, weekly trends, automatic SCALE / HOLD / KEEP / CUT status.
A30: Optimization | B30: Findings, budget reallocation with projected ROAS, next tests.
A32: Legend & honesty note
A33: Blue text | B33: Editable input
A34: Yellow fill | B34: Key assumption to confirm
A35: Green text | B35: Link to another sheet
A36: Black text | B36: Formula
A37: Data note | B37: Benchmarks are illustrative planning ranges. Sample Data is simulated for the case study and is not IKEA Egypt performance data.

Sheet Inputs
A1: Inputs & Assumptions
A2: Blue text = editable input. Yellow fill = key assumption to confirm. Every other sheet reads from here.
A4: Input | B4: Value | C4: Unit | D4: Note / source
A5: Monthly paid media budget | B5: 250000 | C5: EGP | D5: This plan expands to 7 sources + CRM.
A6: Flight length | B6: 30 | C6: days | D6: One test month (Nov 2026).
A7: Average order value (AOV) | B7: 4500 | C7: EGP | D7: Illustrative price point for the New Home Starter Bundle.
A8: Gross margin | B8: 0.35 | C8: % | D8: Illustrative assumption for furniture retail. Drives break-even ROAS.
A9: Break-even ROAS | B9: =1/B8 -> 2.8571429 | C9: x | D9: Formula: 1 / gross margin. Below this a campaign loses money on a last-click basis.
A10: Target ROAS (blended) | B10: 3.5 | C10: x | D10: Business target for the month.
A11: Target CPA | B11: =B7/B10 -> 1285.7143 | C11: EGP | D11: Formula: AOV / target ROAS.
A12: Scale threshold | B12: 1.2 | C12: x target | D12: A campaign is flagged SCALE when ROAS >= target x this value.
A13: Assist-credit threshold | B13: 0.08 | C13: % | D13: Upper-funnel campaigns below break-even are kept only if position-based credit share >= this.
A14: Fatigue threshold (CTR drop W1 to W4) | B14: 0.25 | C14: % | D14: CTR falling more than this between week 1 and week 4 flags creative fatigue.
A15: Scaling efficiency on added budget | B15: 0.85 | C15: % | D15: Diminishing returns haircut applied to extra budget in the reallocation model.
A16: Landing page base URL | B16: https://new-home-starter-bundle.lovable.app/ | C16: URL | D16: Live concept landing page built on Lovable for this project (7-section skeleton). It reads the UTMs and shows them in a tracking debug card.
A17: Offer code (for campaign names) | B17: nhsb | C17: text | D17: nhsb = New Home Starter Bundle.
A18: Flight (YYYYMM) | B18: 202611 | C18: text | D18: Used in every campaign name.

Sheet Funnel & Audiences
A1: Funnel Stages, Audiences & Messaging
A2: Persona: Mariam Adel, first-time furnisher in New Cairo. Excluded segment: gehaz families (carpenter-installment dynamic).
A4: Stage | B4: Mariam's mindset | C4: Campaign objective | D4: Platforms | E4: Audience (include) | F4: Exclude | G4: Message angle | H4: Offer | I4: Primary KPI | J4: Lookback window
A5: TOFU · Awareness | B5: "We just got the keys. Where do we even start?" | C5: Reach / video views, build warm pools | D5: TikTok, YouTube | E5: Age 24-34, Cairo & Giza, New Cairo + 6th of October compounds; interests: home decor, interior design, newly engaged/married; in-market: home furnishings (YouTube) | F5: Existing purchasers 180d; IKEA Family members | G5: Your first apartment, planned in one afternoon | H5: Entry: free Small Space Planning Session | I5: CPM, 2s/6s view rate, thumb-stop rate | J5: n/a (cold)
A6: MOFU · Consideration | B6: "Is IKEA right for our space and our budget?" | C6: Traffic / engagement to room planner and bundle page | D6: Meta (FB+IG), Snapchat | E6: Video viewers 50% (TikTok/YouTube/Meta) 30d; IG/FB engagers 60d; 1% lookalike of purchasers; room-planner starters | F6: Purchasers 180d; add-to-cart 14d (handled in BOFU) | G6: Fixed price, delivered on the day we promise (ownable claim: delivery reliability) | H6: Core: New Home Starter Bundle | I6: CTR, CPC, landing page view rate, planner starts | J6: 30-60 days
A7: BOFU · Conversion | B7: "We are ready, just need a reason to buy now." | C7: Sales / purchase conversion | D7: Google Search, Google PMax/Shopping, Meta Retargeting (catalog) | E7: High-intent keywords (ikea egypt, furniture new cairo, bedroom set price); product feed; view content 30d + add-to-cart 14d | F7: Purchasers 30d; brand-safety negatives (used, second hand, carpenter) | G7: The full starter bundle, delivered and assembled, risk-free | H7: Retargeting: bundle + risk reversal (delivery guarantee, easy returns) | I7: CVR, CPA, ROAS | J7: 7-30 days
A8: CARE · Retention | B8: "The bedroom is done. Now the living room." | C8: Repeat purchase / cross-sell | D8: Email + WhatsApp (IKEA Family) | E8: Purchasers 7-180d; IKEA Family members; abandoned checkout 3d | F8: Unsubscribed / opted out; purchasers in last 7d | G8: Full Apartment Plan: next room, same easy delivery | H8: Room #2 bundle + IKEA Family perk | I8: Repeat rate, ROAS, CTR on sends | J8: 180 days

Sheet Audience & Retargeting
A1: Audience & Retargeting Structure · cold / warm / hot
A2: logic: each temperature gets its own audience, window, exclusions, frequency and message. Pools feed each other from top to bottom.
A4: Temperature | B4: Audience definition | C4: Window | D4: Platforms / campaigns | E4: Exclude | F4: Frequency cap | G4: Message job | H4: Creative (existing assets) | I4: Est. pool size
A5: COLD | B5: Interest + lookalike: 24-34, Cairo & Giza compounds, home decor, newly married; 1% LAL of purchasers | C5: n/a | D5: TikTok C01, YouTube C02, Snapchat C03, Meta LAL inside C04 | E5: Site visitors 30d, purchasers 180d | F5: 2 / week | G5: Problem + aspiration: first apartment, planned in one afternoon | H5: Spark Ads on IKEA room tours, catalog carousels | I5: Large (hundreds of thousands)
A6: WARM | B6: Video viewers 50% (TikTok, YouTube, Meta), IG/FB engagers, landing page visitors without product view, room-planner starters | C6: 30-60 days | D6: Meta C04, TikTok retargeting test | E6: ATC 14d, purchasers 30d | F6: 3 / week | G6: Proof + ownable claim: fixed price, delivered on the promised day | H6: Testimonial-style captions on catalog Reels | I6: Medium (tens of thousands), grows with COLD spend
A7: HOT | B7: View content 30d, add to cart 14d, begin checkout 7d, high-intent searchers | C7: 7-30 days | D7: Meta retargeting C07, Google Search C05, PMax C06 | E7: Purchasers 30d | F7: 4-5 / week, cap 3 / day | G7: Risk reversal + urgency: delivery guarantee, cash on delivery, easy returns | H7: Dynamic product ads with COD + delivery-date overlay text | I7: Small (low thousands), capped by WARM size
A8: CUSTOMERS | B8: Purchasers 7-180d, IKEA Family members | C8: 180 days | D8: Email + WhatsApp C08 | E8: Purchased in last 7d, opted out | F8: 1-2 messages / week | G8: Full Apartment Plan: the next room, same easy delivery | H8: Text templates, no design needed | I8: Grows with every order
A10: Retargeting sequence (hot path, by days since last action)
A11: Days since action | B11: Trigger | C11: Channel | D11: Message | E11: Goal
A12: 0-1 | B12: Begin checkout, no purchase | C12: WhatsApp (C08 flow) | D12: "Your bundle is saved. Want us to hold your delivery date?" | E12: Recover checkout
A13: 1-3 | B13: Add to cart, no purchase | C13: Meta DPA (C07) | D13: Product seen + 'Pay cash on delivery' | E13: Remove payment friction
A14: 4-14 | B14: Add to cart or view content | C14: Meta DPA + Google remarketing via PMax | D14: Delivery date guarantee + illustrative review | E14: Remove trust friction
A15: 15-30 | B15: View content only | C15: Meta (C04 warm) | D15: Free planning session (Entry offer) | E15: Re-open the journey with a low-commitment offer
A16: Purchase +7 | B16: Purchase | C16: WhatsApp | D16: Delivery + assembly check-in, review request | E16: Satisfaction, social proof
A17: Purchase +30 | B17: Purchase | C17: Email + WhatsApp | D17: Room #2 checklist from the Full Apartment Plan | E17: Fix the Activation-to-Retention leak

Sheet Media Plan
A1: Multi-Source Paid Media Plan · 30 days
A2: Blue = benchmark inputs (illustrative Egypt ranges, adjust to your account history). Black = formulas. Formats reuse existing IKEA assets: no new production.
A4: ID | B4: Platform | C4: Attribution channel | D4: Stage | E4: 70/20/10 tier | F4: Objective / bid strategy | G4: Audience | H4: Format (existing assets) | I4: Budget share | J4: Budget (EGP) | K4: Daily (EGP) | L4: CPM (EGP) | M4: CTR | N4: CVR (click to purchase) | O4: Est. impressions | P4: Est. clicks | Q4: Est. CPC | R4: Est. purchases | S4: Est. revenue | T4: Est. ROAS | U4: Est. CPA | V4: Primary KPI | W4: Learning objective (what this line must teach us)
A5: C01 | B5: TikTok | C5: TikTok | D5: TOFU | E5: Growth (20) | F5: Reach then Video Views, max delivery | G5: Cold 24-34, Cairo/Giza compounds, home decor + newly married | H5: Spark Ads boosting IKEA organic room tours | I5: 0.15 | J5: =I5*Inputs!$B$5 -> 37500 | K5: =J5/Inputs!$B$6 -> 1250 | L5: 30 | M5: 0.006 | N5: 0.001 | O5: =J5/L5*1000 -> 1250000 | P5: =O5*M5 -> 7500 | Q5: =IFERROR(J5/P5,0) -> 5 | R5: =P5*N5 -> 7.5 | S5: =R5*Inputs!$B$7 -> 33750 | T5: =IFERROR(S5/J5,0) -> 0.9 | U5: =IFERROR(J5/R5,0) -> 5000 | V5: CPM, 6s view rate | W5: Can TikTok build a warm pool cheaply enough to feed Search and retargeting? Judge on CPM, 6s view rate and assist share.
A6: C02 | B6: YouTube | C6: YouTube | D6: TOFU | E6: Test (10) | F6: Video reach (Bumper 6s), target CPM | G6: In-market: home furnishings, Egypt | H6: Cut-downs of IKEA global brand films | I6: 0.05 | J6: =I6*Inputs!$B$5 -> 12500 | K6: =J6/Inputs!$B$6 -> 416.66667 | L6: 45 | M6: 0.003 | N6: 0.0025 | O6: =J6/L6*1000 -> 277777.78 | P6: =O6*M6 -> 833.33333 | Q6: =IFERROR(J6/P6,0) -> 15 | R6: =P6*N6 -> 2.0833333 | S6: =R6*Inputs!$B$7 -> 9375 | T6: =IFERROR(S6/J6,0) -> 0.75 | U6: =IFERROR(J6/R6,0) -> 6000 | V6: CPM, view rate | W6: Do YouTube Bumpers add reach TikTok misses at an acceptable CPM? Test line.
A7: C03 | B7: Snapchat | C7: Snapchat | D7: MOFU | E7: Test (10) | F7: Traffic, landing page views | G7: Lifestyle 20-30, Cairo/Giza | H7: Single image / collection ads from catalog | I7: 0.05 | J7: =I7*Inputs!$B$5 -> 12500 | K7: =J7/Inputs!$B$6 -> 416.66667 | L7: 25 | M7: 0.005 | N7: 0.0012 | O7: =J7/L7*1000 -> 500000 | P7: =O7*M7 -> 2500 | Q7: =IFERROR(J7/P7,0) -> 5 | R7: =P7*N7 -> 3 | S7: =R7*Inputs!$B$7 -> 13500 | T7: =IFERROR(S7/J7,0) -> 1.08 | U7: =IFERROR(J7/R7,0) -> 4166.6667 | V7: CTR, CPC | W7: Does Snapchat's 20-30 audience turn into planner visits for a first-home offer? Test line.
A8: C04 | B8: Meta | C8: Meta Prospecting | D8: MOFU | E8: Proven (70) | F8: Traffic to room planner + bundle, LPV | G8: Video viewers 50% 30d, engagers 60d, LAL 1% buyers | H8: Reels + carousel from existing catalog shots | I8: 0.2 | J8: =I8*Inputs!$B$5 -> 50000 | K8: =J8/Inputs!$B$6 -> 1666.6667 | L8: 55 | M8: 0.011 | N8: 0.003 | O8: =J8/L8*1000 -> 909090.91 | P8: =O8*M8 -> 10000 | Q8: =IFERROR(J8/P8,0) -> 5 | R8: =P8*N8 -> 30 | S8: =R8*Inputs!$B$7 -> 135000 | T8: =IFERROR(S8/J8,0) -> 2.7 | U8: =IFERROR(J8/R8,0) -> 1666.6667 | V8: CTR, CPC, LPV | W8: Which angle (delivery, price, planning) wins on CTR and cost per landing page view?
A9: C05 | B9: Google Search | C9: Google Search | D9: BOFU | E9: Proven (70) | F9: Sales, Max conversion value (tROAS later) | G9: Brand + generic high-intent keywords | H9: Responsive search ads + sitelinks | I9: 0.22 | J9: =I9*Inputs!$B$5 -> 55000 | K9: =J9/Inputs!$B$6 -> 1833.3333 | L9: 360 | M9: 0.06 | N9: 0.0075 | O9: =J9/L9*1000 -> 152777.78 | P9: =O9*M9 -> 9166.6667 | Q9: =IFERROR(J9/P9,0) -> 6 | R9: =P9*N9 -> 68.75 | S9: =R9*Inputs!$B$7 -> 309375 | T9: =IFERROR(S9/J9,0) -> 5.625 | U9: =IFERROR(J9/R9,0) -> 800 | V9: CVR, CPA, ROAS | W9: How much high-intent demand exists, and what CPA can Search hold as budget grows?
A10: C06 | B10: Google PMax | C10: Google PMax | D10: BOFU | E10: Proven (70) | F10: Sales, Max conversion value, feed-only | G10: Product feed: bedroom, living, kitchen bundles | H10: Shopping feed (no new creative) | I10: 0.13 | J10: =I10*Inputs!$B$5 -> 32500 | K10: =J10/Inputs!$B$6 -> 1083.3333 | L10: 70 | M10: 0.015 | N10: 0.004 | O10: =J10/L10*1000 -> 464285.71 | P10: =O10*M10 -> 6964.2857 | Q10: =IFERROR(J10/P10,0) -> 4.6666667 | R10: =P10*N10 -> 27.857143 | S10: =R10*Inputs!$B$7 -> 125357.14 | T10: =IFERROR(S10/J10,0) -> 3.8571429 | U10: =IFERROR(J10/R10,0) -> 1166.6667 | V10: ROAS | W10: Can a feed-only PMax hit target ROAS without new creative?
A11: C07 | B11: Meta | C11: Meta Retargeting | D11: BOFU | E11: Proven (70) | F11: Sales, Advantage+ catalog (DPA) | G11: View content 30d + ATC 14d, excl. buyers 30d | H11: Dynamic product ads | I11: 0.15 | J11: =I11*Inputs!$B$5 -> 37500 | K11: =J11/Inputs!$B$6 -> 1250 | L11: 80 | M11: 0.018 | N11: 0.007 | O11: =J11/L11*1000 -> 468750 | P11: =O11*M11 -> 8437.5 | Q11: =IFERROR(J11/P11,0) -> 4.4444444 | R11: =P11*N11 -> 59.0625 | S11: =R11*Inputs!$B$7 -> 265781.25 | T11: =IFERROR(S11/J11,0) -> 7.0875 | U11: =IFERROR(J11/R11,0) -> 634.92063 | V11: ROAS, frequency | W11: Which window and frequency (7 / 14 / 30d) maximise retargeting ROAS before fatigue?
A12: C08 | B12: Email + WhatsApp | C12: Email/WhatsApp | D12: CARE | E12: Growth (20) | F12: Automated flows: cart, post-purchase, room #2 | G12: Buyers 7-180d, IKEA Family, abandoned checkout 3d | H12: Text templates (no design) | I12: 0.05 | J12: =I12*Inputs!$B$5 -> 12500 | K12: =J12/Inputs!$B$6 -> 416.66667 | L12: 600 | M12: 0.08 | N12: 0.02 | O12: =J12/L12*1000 -> 20833.333 | P12: =O12*M12 -> 1666.6667 | Q12: =IFERROR(J12/P12,0) -> 7.5 | R12: =P12*N12 -> 33.333333 | S12: =R12*Inputs!$B$7 -> 150000 | T12: =IFERROR(S12/J12,0) -> 12 | U12: =IFERROR(J12/R12,0) -> 375 | V12: Repeat rate, ROAS | W12: What share of buyers order a second room within 90 days?
A13: TOTAL / BLENDED | I13: =SUM(I5:I12) -> 1 | J13: =SUM(J5:J12) -> 250000 | K13: =SUM(K5:K12) -> 8333.3333 | O13: =SUM(O5:O12) -> 4043515.5 | P13: =SUM(P5:P12) -> 47068.452 | Q13: =IFERROR(J13/P13,0) -> 5.3114132 | R13: =SUM(R5:R12) -> 231.58631 | S13: =SUM(S5:S12) -> 1042138.4 | T13: =IFERROR(S13/J13,0) -> 4.1685536 | U13: =IFERROR(J13/R13,0) -> 1079.5111
I14: =IF(ROUND(I13,4)=1,"OK: shares sum to 100%","CHECK: shares must sum to 100%") -> OK: shares sum to 100%
A16: Notes
A17: 1. Upper-funnel lines (TikTok, YouTube) are not expected to hit ROAS on last click. They are judged on CPM/view rate here and on assist credit in the Attribution sheet.
A18: 2. C08 'CPM' = cost per 1,000 sends (WhatsApp Business conversation fees + email tool), 'CTR' = click rate on sends.
A19: 3. CPM / CTR / CVR are illustrative planning benchmarks, not IKEA Egypt actuals. Replace them with account history once available.
A20: 4. Google Ads keeps auto-tagging (gclid) ON; UTMs are added through the Final URL suffix so GA4, Looker Studio and the CRM all read the same campaign names.

Sheet Budget Split
A1: Budget Split
A2: All values are formulas reading the Media Plan. Change shares there.
A4: 1. By funnel stage
A5: Stage | B5: Budget (EGP) | C5: Share | D5: Est. revenue | E5: Est. ROAS | F5: Role
A6: TOFU | B6: =SUMIFS('Media Plan'!$J$5:$J$12,'Media Plan'!$D$5:$D$12,A6) -> 50000 | C6: =B6/Inputs!$B$5 -> 0.2 | D6: =SUMIFS('Media Plan'!$S$5:$S$12,'Media Plan'!$D$5:$D$12,A6) -> 43125 | E6: =IFERROR(D6/B6,0) -> 0.8625 | F6: Create demand, fill warm pools
A7: MOFU | B7: =SUMIFS('Media Plan'!$J$5:$J$12,'Media Plan'!$D$5:$D$12,A7) -> 62500 | C7: =B7/Inputs!$B$5 -> 0.25 | D7: =SUMIFS('Media Plan'!$S$5:$S$12,'Media Plan'!$D$5:$D$12,A7) -> 148500 | E7: =IFERROR(D7/B7,0) -> 2.376 | F7: Educate, drive planner + bundle visits
A8: BOFU | B8: =SUMIFS('Media Plan'!$J$5:$J$12,'Media Plan'!$D$5:$D$12,A8) -> 125000 | C8: =B8/Inputs!$B$5 -> 0.5 | D8: =SUMIFS('Media Plan'!$S$5:$S$12,'Media Plan'!$D$5:$D$12,A8) -> 700513.39 | E8: =IFERROR(D8/B8,0) -> 5.6041071 | F8: Capture demand, sell
A9: CARE | B9: =SUMIFS('Media Plan'!$J$5:$J$12,'Media Plan'!$D$5:$D$12,A9) -> 12500 | C9: =B9/Inputs!$B$5 -> 0.05 | D9: =SUMIFS('Media Plan'!$S$5:$S$12,'Media Plan'!$D$5:$D$12,A9) -> 150000 | E9: =IFERROR(D9/B9,0) -> 12 | F9: Repeat purchase, Full Apartment Plan
A10: Total | B10: =SUM(B6:B9) -> 250000 | C10: =SUM(C6:C9) -> 1 | D10: =SUM(D6:D9) -> 1042138.4 | E10: =IFERROR(D10/B10,0) -> 4.1685536
A12: 2. By test tier (70/20/10 rule )
A13: Tier | B13: Planned share | C13: Rule share | D13: Gap | E13: Platforms in tier
A14: Proven (70) | B14: =SUMIFS('Media Plan'!$I$5:$I$12,'Media Plan'!$E$5:$E$12,A14) -> 0.7 | C14: 0.7 | D14: =B14-C14 -> 0 | E14: Meta MOFU, Google Search, PMax, Meta Retargeting
A15: Growth (20) | B15: =SUMIFS('Media Plan'!$I$5:$I$12,'Media Plan'!$E$5:$E$12,A15) -> 0.2 | C15: 0.2 | D15: =B15-C15 -> 0 | E15: TikTok, Email + WhatsApp
A16: Test (10) | B16: =SUMIFS('Media Plan'!$I$5:$I$12,'Media Plan'!$E$5:$E$12,A16) -> 0.1 | C16: 0.1 | D16: =B16-C16 -> 0 | E16: YouTube, Snapchat
A18: 3. By platform
A19: Platform | B19: Budget (EGP) | C19: Share
A20: TikTok | B20: =SUMIFS('Media Plan'!$J$5:$J$12,'Media Plan'!$B$5:$B$12,A20) -> 37500 | C20: =B20/Inputs!$B$5 -> 0.15
A21: YouTube | B21: =SUMIFS('Media Plan'!$J$5:$J$12,'Media Plan'!$B$5:$B$12,A21) -> 12500 | C21: =B21/Inputs!$B$5 -> 0.05
A22: Snapchat | B22: =SUMIFS('Media Plan'!$J$5:$J$12,'Media Plan'!$B$5:$B$12,A22) -> 12500 | C22: =B22/Inputs!$B$5 -> 0.05
A23: Meta | B23: =SUMIFS('Media Plan'!$J$5:$J$12,'Media Plan'!$B$5:$B$12,A23) -> 87500 | C23: =B23/Inputs!$B$5 -> 0.35
A24: Google Search | B24: =SUMIFS('Media Plan'!$J$5:$J$12,'Media Plan'!$B$5:$B$12,A24) -> 55000 | C24: =B24/Inputs!$B$5 -> 0.22
A25: Google PMax | B25: =SUMIFS('Media Plan'!$J$5:$J$12,'Media Plan'!$B$5:$B$12,A25) -> 32500 | C25: =B25/Inputs!$B$5 -> 0.13
A26: Email + WhatsApp | B26: =SUMIFS('Media Plan'!$J$5:$J$12,'Media Plan'!$B$5:$B$12,A26) -> 12500 | C26: =B26/Inputs!$B$5 -> 0.05
A28: 4. Weekly pacing (even daily pacing)
A29: Week | B29: Days | C29: Planned spend (EGP) | D29: Cumulative | E29: Cumulative %
A30: Week 1 | B30: 7 | C30: =Inputs!$B$5/Inputs!$B$6*B30 -> 58333.333 | D30: =SUM($C$30:C30) -> 58333.333 | E30: =D30/Inputs!$B$5 -> 0.23333333
A31: Week 2 | B31: 7 | C31: =Inputs!$B$5/Inputs!$B$6*B31 -> 58333.333 | D31: =SUM($C$30:C31) -> 116666.67 | E31: =D31/Inputs!$B$5 -> 0.46666667
A32: Week 3 | B32: 7 | C32: =Inputs!$B$5/Inputs!$B$6*B32 -> 58333.333 | D32: =SUM($C$30:C32) -> 175000 | E32: =D32/Inputs!$B$5 -> 0.7
A33: Week 4 | B33: 9 | C33: =Inputs!$B$5/Inputs!$B$6*B33 -> 75000 | D33: =SUM($C$30:C33) -> 250000 | E33: =D33/Inputs!$B$5 -> 1
A34: Week 4 includes days 29-30 so the month closes in four reporting weeks.

Sheet Creative Testing
A1: Offer Ladder, Ad Concepts & Creative Testing Plan
A2: Copy-led concepts on existing IKEA assets (catalog shots, organic room tours): no new photo or video production needed.
A4: 1. Offer ladder
A5: Rung | B5: Offer | C5: Value stack | D5: Risk reversal | E5: Used in
A6: Entry | B6: Free Small Space Planning Session (room planner, 30 min) | C6: Personal floor plan + shopping list for the whole apartment | D6: No purchase needed | E6: COLD / WARM: C01, C02, C04
A7: Core | B7: New Home Starter Bundle, from 4,500 EGP | C7: Bedroom, living and kitchen essentials in one order, one delivery date | D7: Delivery date guarantee, easy returns | E7: HOT: C05, C06
A8: Retargeting | B8: Bundle + cash on delivery + assembly booked on the delivery day | C8: Same bundle, zero payment and assembly friction | D8: Pay on delivery, assembly slot confirmed by WhatsApp | E8: HOT: C07, checkout recovery
A9: Retention | B9: Full Apartment Plan: room #2 checklist + IKEA Family perk | C9: Next room planned in the same style | D9: Same delivery guarantee | E9: CUSTOMERS: C08
A11: 2. Ad concepts (copy only, existing assets)
A12: # | B12: Campaign | C12: Angle | D12: Hook (first line / first 2s) | E12: Primary text | F12: CTA | G12: Asset source
A13: A1 | B13: C01 TikTok | C13: Aspiration | D13: "We got the keys on Thursday. By Saturday it looked like this." | E13: Your first apartment, planned in one afternoon. Free planning session with the room planner. | F13: Book free session | G13: Spark Ad on an IKEA organic room tour
A14: A2 | B14: C01 TikTok | C14: Problem | D14: "Three carpenters, three different dates, zero furniture." | E14: One plan, one bundle, one delivery date you can count on. | F14: See the bundle | G14: Spark Ad, room tour cut
A15: A3 | B15: C01 TikTok | C15: Social proof | D15: "POV: your compound neighbors ask who did your living room." | E15: The New Home Starter Bundle: bedroom, living and kitchen essentials. | F15: Plan my apartment | G15: Spark Ad, before/after organic post
A16: A4 | B16: C04 Meta | C16: Delivery promise | D16: Delivered on the day we promise. Assembled the same day. | E16: Stop chasing delivery windows. The Starter Bundle comes with a delivery date guarantee. | F16: Learn more | G16: Catalog Reel
A17: A5 | B17: C04 Meta | C17: Price clarity | D17: Your whole first apartment, from 4,500 EGP. No surprises. | E17: Fixed price, no hidden costs, cash on delivery available. | F17: Shop now | G17: Catalog carousel
A18: A6 | B18: C04 Meta | C18: Planning | D18: Not sure what fits a 120 m² apartment? We'll plan it with you. | E18: Free 30-minute planning session with the IKEA room planner. | F18: Book now | G18: Carousel of planner screenshots
A19: A7 | B19: C05 Search | C19: Intent | D19: Headline: Furnish Your New Apartment | Starter Bundle From 4,500 EGP | E19: Bedroom, living & kitchen essentials. Delivery date guaranteed. Cash on delivery. | F19: Shop the bundle | G19: Responsive search ad
A20: A8 | B20: C07 Meta DPA | C20: Risk reversal | D20: Still thinking about it? Pay cash on delivery. | E20: Your saved items, delivered on the date you choose, with easy returns. | F20: Complete order | G20: Dynamic product ad
A21: A9 | B21: C08 WhatsApp | C21: Retention | D21: "Bedroom done? Let's plan the living room." | E21: Your Full Apartment Plan is ready: room #2 checklist + IKEA Family perk. | F21: See room #2 | G21: Text template
A23: 3. Creative testing plan (one variable at a time)
A24: Test | B24: Campaign | C24: Variable tested | D24: Variants | E24: Held constant | F24: Budget split | G24: Success metric | H24: Stop / decision rule
A25: T1 Hook test | B25: C01 TikTok | C25: Opening hook | D25: A1 vs A2 vs A3 | E25: Audience, asset family, CTA, bid | F25: Equal thirds of C01 for 7 days | G25: 6s view rate, CPM | H25: Winner needs >= 15% higher 6s view rate after 10,000 impressions per arm; loser paused
A26: T2 Angle test | B26: C04 Meta | C26: Message angle | D26: A4 delivery vs A5 price vs A6 planning | E26: Warm audience, format, landing page | F26: Equal thirds, ad-set level | G26: CTR, cost per landing page view | H26: Run 14 days or 1,000 clicks per arm; keep the top angle, reuse it in Search ad copy
A27: T3 Creative refresh | B27: C04 Meta | C27: Rotation cadence | D27: 3 static Reels vs 6 assets rotated every 10 days | E27: Audience, budget, objective | F27: 50 / 50 | G27: CTR trend W1 to W4, CPM | H27: If rotation keeps CTR drop under 25%, make it standard (fatigue rule on Dashboard)
A28: T4 DPA overlay | B28: C07 Meta | C28: Overlay text | D28: 'Cash on delivery' vs 'Delivered on your date' vs none | E28: Catalog, audience windows | F28: Equal thirds | G28: ROAS, CVR | H28: Call after 50 purchases per arm or 21 days; else keep current
A29: T5 RSA pinning | B29: C05 Search | C29: Headline 1 | D29: Price-led vs delivery-led pinned headline | E29: Keywords, bids, landing page | F29: Campaign experiment 50 / 50 | G29: CTR, CVR, CPA | H29: Use Google Ads experiment significance (95%)
A30: T6 WhatsApp copy | B30: C08 | C30: Opening line | D30: Question vs checklist-first | E30: Audience, send time | F30: 50 / 50 of buyers 30d | G30: Click rate, room #2 orders | H30: After 500 sends per arm; keep the higher click rate
A31: Rule: test one variable at a time, keep the audience and budget fixed, and decide only after the minimum sample is reached. No mid-test edits.

Sheet UTM Builder
A1: UTM Convention & Link Builder
A2: rules: lowercase only, underscores not spaces, values picked from a fixed list. Campaign = goal_audience_offer_yyyymm. The full URL builds itself.
A4: 1. Naming dictionary
A5: Parameter | B5: Question it answers | C5: Allowed values / example | D5: Why
A6: utm_source | B6: Where from? | C6: meta · tiktok · google · youtube · snapchat · email · whatsapp | D6: One value per platform. 'Meta' and 'meta' would split into two sources in GA4.
A7: utm_medium | B7: How? | C7: cpc (all paid ads) · email · whatsapp · social (organic only) | D7: cpc + a social source lands in GA4 'Paid Social'; cpc + google lands in 'Paid Search'. whatsapp needs a custom channel group.
A8: utm_campaign | B8: Which initiative? | C8: goal_audience_offer_yyyymm, e.g. awareness_firsthome_nhsb_202611 | D8: Goal first, audience second, date last, plus the offer code.
A9: utm_content | B9: Which creative? | C9: format_angle_version, e.g. spark_first_apartment_v1 | D9: Shows which angle wins inside the same campaign.
A10: utm_term | B10: Which keyword? | C10: Search only: furniture_new_cairo | D10: Niche. Left empty for social, CRM and feed campaigns.
A12: 2. Link builder
A13: ID | B13: utm_source | C13: utm_medium | D13: Goal | E13: Audience code | F13: utm_content | G13: utm_term | H13: utm_campaign (auto) | I13: Final URL (auto) | J13: Check
A14: C01 | B14: tiktok | C14: cpc | D14: awareness | E14: firsthome | F14: spark_first_apartment_v1 | H14: =LOWER(SUBSTITUTE(TRIM(D14)&"_"&TRIM(E14)," ","_")&"_"&Inputs!$B$17&"_"&Inputs!$B$18) -> awareness_firsthome_nhsb_202611 | I14: =Inputs!$B$16&IF(ISNUMBER(FIND("?",Inputs!$B$16)),"&","?")&"utm_source="&LOWER(B14)&"&utm_medium="&LOWER(C14)&"&utm_campaign="&H14&"&utm_content="&LOWER(SUBSTITUTE(F14," ","_"))&IF(G14="","","&utm_term="&LOWER(SUBSTITUTE(G14," ","_"))) -> https://new-home-starter-bundle.lovable.app/?utm_source=tiktok&utm_medium=cpc&utm_campaign=awareness_firsthome_nhsb_202611&utm_content=spark_first_apartment_v1 | J14: =IF(OR(B14="",C14="",D14="",E14="",F14=""),"MISSING",IF(OR(ISNUMBER(FIND(" ",I14)),EXACT(I14,LOWER(I14))=FALSE()),"FIX CASE/SPACE","OK")) -> OK
A15: C02 | B15: youtube | C15: cpc | D15: awareness | E15: inmarkethome | F15: bumper_one_afternoon_v1 | H15: =LOWER(SUBSTITUTE(TRIM(D15)&"_"&TRIM(E15)," ","_")&"_"&Inputs!$B$17&"_"&Inputs!$B$18) -> awareness_inmarkethome_nhsb_202611 | I15: =Inputs!$B$16&IF(ISNUMBER(FIND("?",Inputs!$B$16)),"&","?")&"utm_source="&LOWER(B15)&"&utm_medium="&LOWER(C15)&"&utm_campaign="&H15&"&utm_content="&LOWER(SUBSTITUTE(F15," ","_"))&IF(G15="","","&utm_term="&LOWER(SUBSTITUTE(G15," ","_"))) -> https://new-home-starter-bundle.lovable.app/?utm_source=youtube&utm_medium=cpc&utm_campaign=awareness_inmarkethome_nhsb_202611&utm_content=bumper_one_afternoon_v1 | J15: =IF(OR(B15="",C15="",D15="",E15="",F15=""),"MISSING",IF(OR(ISNUMBER(FIND(" ",I15)),EXACT(I15,LOWER(I15))=FALSE()),"FIX CASE/SPACE","OK")) -> OK
A16: C03 | B16: snapchat | C16: cpc | D16: consideration | E16: young20to30 | F16: collection_bundle_v1 | H16: =LOWER(SUBSTITUTE(TRIM(D16)&"_"&TRIM(E16)," ","_")&"_"&Inputs!$B$17&"_"&Inputs!$B$18) -> consideration_young20to30_nhsb_202611 | I16: =Inputs!$B$16&IF(ISNUMBER(FIND("?",Inputs!$B$16)),"&","?")&"utm_source="&LOWER(B16)&"&utm_medium="&LOWER(C16)&"&utm_campaign="&H16&"&utm_content="&LOWER(SUBSTITUTE(F16," ","_"))&IF(G16="","","&utm_term="&LOWER(SUBSTITUTE(G16," ","_"))) -> https://new-home-starter-bundle.lovable.app/?utm_source=snapchat&utm_medium=cpc&utm_campaign=consideration_young20to30_nhsb_202611&utm_content=collection_bundle_v1 | J16: =IF(OR(B16="",C16="",D16="",E16="",F16=""),"MISSING",IF(OR(ISNUMBER(FIND(" ",I16)),EXACT(I16,LOWER(I16))=FALSE()),"FIX CASE/SPACE","OK")) -> OK
A17: C04 | B17: meta | C17: cpc | D17: consideration | E17: warmpool | F17: reel_delivery_promise_v1 | H17: =LOWER(SUBSTITUTE(TRIM(D17)&"_"&TRIM(E17)," ","_")&"_"&Inputs!$B$17&"_"&Inputs!$B$18) -> consideration_warmpool_nhsb_202611 | I17: =Inputs!$B$16&IF(ISNUMBER(FIND("?",Inputs!$B$16)),"&","?")&"utm_source="&LOWER(B17)&"&utm_medium="&LOWER(C17)&"&utm_campaign="&H17&"&utm_content="&LOWER(SUBSTITUTE(F17," ","_"))&IF(G17="","","&utm_term="&LOWER(SUBSTITUTE(G17," ","_"))) -> https://new-home-starter-bundle.lovable.app/?utm_source=meta&utm_medium=cpc&utm_campaign=consideration_warmpool_nhsb_202611&utm_content=reel_delivery_promise_v1 | J17: =IF(OR(B17="",C17="",D17="",E17="",F17=""),"MISSING",IF(OR(ISNUMBER(FIND(" ",I17)),EXACT(I17,LOWER(I17))=FALSE()),"FIX CASE/SPACE","OK")) -> OK
A18: C05 | B18: google | C18: cpc | D18: purchase | E18: intent | F18: rsa_bundle_price_v1 | G18: furniture_new_cairo | H18: =LOWER(SUBSTITUTE(TRIM(D18)&"_"&TRIM(E18)," ","_")&"_"&Inputs!$B$17&"_"&Inputs!$B$18) -> purchase_intent_nhsb_202611 | I18: =Inputs!$B$16&IF(ISNUMBER(FIND("?",Inputs!$B$16)),"&","?")&"utm_source="&LOWER(B18)&"&utm_medium="&LOWER(C18)&"&utm_campaign="&H18&"&utm_content="&LOWER(SUBSTITUTE(F18," ","_"))&IF(G18="","","&utm_term="&LOWER(SUBSTITUTE(G18," ","_"))) -> https://new-home-starter-bundle.lovable.app/?utm_source=google&utm_medium=cpc&utm_campaign=purchase_intent_nhsb_202611&utm_content=rsa_bundle_price_v1&utm_term=furniture_new_cairo | J18: =IF(OR(B18="",C18="",D18="",E18="",F18=""),"MISSING",IF(OR(ISNUMBER(FIND(" ",I18)),EXACT(I18,LOWER(I18))=FALSE()),"FIX CASE/SPACE","OK")) -> OK
A19: C06 | B19: google | C19: cpc | D19: purchase | E19: feed | F19: pmax_bedroom_v1 | H19: =LOWER(SUBSTITUTE(TRIM(D19)&"_"&TRIM(E19)," ","_")&"_"&Inputs!$B$17&"_"&Inputs!$B$18) -> purchase_feed_nhsb_202611 | I19: =Inputs!$B$16&IF(ISNUMBER(FIND("?",Inputs!$B$16)),"&","?")&"utm_source="&LOWER(B19)&"&utm_medium="&LOWER(C19)&"&utm_campaign="&H19&"&utm_content="&LOWER(SUBSTITUTE(F19," ","_"))&IF(G19="","","&utm_term="&LOWER(SUBSTITUTE(G19," ","_"))) -> https://new-home-starter-bundle.lovable.app/?utm_source=google&utm_medium=cpc&utm_campaign=purchase_feed_nhsb_202611&utm_content=pmax_bedroom_v1 | J19: =IF(OR(B19="",C19="",D19="",E19="",F19=""),"MISSING",IF(OR(ISNUMBER(FIND(" ",I19)),EXACT(I19,LOWER(I19))=FALSE()),"FIX CASE/SPACE","OK")) -> OK
A20: C07 | B20: meta | C20: cpc | D20: purchase | E20: carts14d | F20: dpa_risk_free_v1 | H20: =LOWER(SUBSTITUTE(TRIM(D20)&"_"&TRIM(E20)," ","_")&"_"&Inputs!$B$17&"_"&Inputs!$B$18) -> purchase_carts14d_nhsb_202611 | I20: =Inputs!$B$16&IF(ISNUMBER(FIND("?",Inputs!$B$16)),"&","?")&"utm_source="&LOWER(B20)&"&utm_medium="&LOWER(C20)&"&utm_campaign="&H20&"&utm_content="&LOWER(SUBSTITUTE(F20," ","_"))&IF(G20="","","&utm_term="&LOWER(SUBSTITUTE(G20," ","_"))) -> https://new-home-starter-bundle.lovable.app/?utm_source=meta&utm_medium=cpc&utm_campaign=purchase_carts14d_nhsb_202611&utm_content=dpa_risk_free_v1 | J20: =IF(OR(B20="",C20="",D20="",E20="",F20=""),"MISSING",IF(OR(ISNUMBER(FIND(" ",I20)),EXACT(I20,LOWER(I20))=FALSE()),"FIX CASE/SPACE","OK")) -> OK
A21: C08 | B21: whatsapp | C21: whatsapp | D21: retention | E21: buyers | F21: flow_room2_v1 | H21: =LOWER(SUBSTITUTE(TRIM(D21)&"_"&TRIM(E21)," ","_")&"_"&Inputs!$B$17&"_"&Inputs!$B$18) -> retention_buyers_nhsb_202611 | I21: =Inputs!$B$16&IF(ISNUMBER(FIND("?",Inputs!$B$16)),"&","?")&"utm_source="&LOWER(B21)&"&utm_medium="&LOWER(C21)&"&utm_campaign="&H21&"&utm_content="&LOWER(SUBSTITUTE(F21," ","_"))&IF(G21="","","&utm_term="&LOWER(SUBSTITUTE(G21," ","_"))) -> https://new-home-starter-bundle.lovable.app/?utm_source=whatsapp&utm_medium=whatsapp&utm_campaign=retention_buyers_nhsb_202611&utm_content=flow_room2_v1 | J21: =IF(OR(B21="",C21="",D21="",E21="",F21=""),"MISSING",IF(OR(ISNUMBER(FIND(" ",I21)),EXACT(I21,LOWER(I21))=FALSE()),"FIX CASE/SPACE","OK")) -> OK
A22: C08 | B22: email | C22: email | D22: recovery | E22: cartabandon | F22: flow_cart_v1 | H22: =LOWER(SUBSTITUTE(TRIM(D22)&"_"&TRIM(E22)," ","_")&"_"&Inputs!$B$17&"_"&Inputs!$B$18) -> recovery_cartabandon_nhsb_202611 | I22: =Inputs!$B$16&IF(ISNUMBER(FIND("?",Inputs!$B$16)),"&","?")&"utm_source="&LOWER(B22)&"&utm_medium="&LOWER(C22)&"&utm_campaign="&H22&"&utm_content="&LOWER(SUBSTITUTE(F22," ","_"))&IF(G22="","","&utm_term="&LOWER(SUBSTITUTE(G22," ","_"))) -> https://new-home-starter-bundle.lovable.app/?utm_source=email&utm_medium=email&utm_campaign=recovery_cartabandon_nhsb_202611&utm_content=flow_cart_v1 | J22: =IF(OR(B22="",C22="",D22="",E22="",F22=""),"MISSING",IF(OR(ISNUMBER(FIND(" ",I22)),EXACT(I22,LOWER(I22))=FALSE()),"FIX CASE/SPACE","OK")) -> OK
H23: =IF(D23="","",LOWER(SUBSTITUTE(TRIM(D23)&"_"&TRIM(E23)," ","_")&"_"&Inputs!$B$17&"_"&Inputs!$B$18)) | I23: =IF(B23="","",Inputs!$B$16&IF(ISNUMBER(FIND("?",Inputs!$B$16)),"&","?")&"utm_source="&LOWER(B23)&"&utm_medium="&LOWER(C23)&"&utm_campaign="&H23&"&utm_content="&LOWER(SUBSTITUTE(F23," ","_"))&IF(G23="","","&utm_term="&LOWER(SUBSTITUTE(G23," ","_")))) | J23: =IF(B23="","",IF(OR(C23="",D23="",E23="",F23=""),"MISSING",IF(OR(ISNUMBER(FIND(" ",I23)),EXACT(I23,LOWER(I23))=FALSE()),"FIX CASE/SPACE","OK")))
H24: =IF(D24="","",LOWER(SUBSTITUTE(TRIM(D24)&"_"&TRIM(E24)," ","_")&"_"&Inputs!$B$17&"_"&Inputs!$B$18)) | I24: =IF(B24="","",Inputs!$B$16&IF(ISNUMBER(FIND("?",Inputs!$B$16)),"&","?")&"utm_source="&LOWER(B24)&"&utm_medium="&LOWER(C24)&"&utm_campaign="&H24&"&utm_content="&LOWER(SUBSTITUTE(F24," ","_"))&IF(G24="","","&utm_term="&LOWER(SUBSTITUTE(G24," ","_")))) | J24: =IF(B24="","",IF(OR(C24="",D24="",E24="",F24=""),"MISSING",IF(OR(ISNUMBER(FIND(" ",I24)),EXACT(I24,LOWER(I24))=FALSE()),"FIX CASE/SPACE","OK")))
H25: =IF(D25="","",LOWER(SUBSTITUTE(TRIM(D25)&"_"&TRIM(E25)," ","_")&"_"&Inputs!$B$17&"_"&Inputs!$B$18)) | I25: =IF(B25="","",Inputs!$B$16&IF(ISNUMBER(FIND("?",Inputs!$B$16)),"&","?")&"utm_source="&LOWER(B25)&"&utm_medium="&LOWER(C25)&"&utm_campaign="&H25&"&utm_content="&LOWER(SUBSTITUTE(F25," ","_"))&IF(G25="","","&utm_term="&LOWER(SUBSTITUTE(G25," ","_")))) | J25: =IF(B25="","",IF(OR(C25="",D25="",E25="",F25=""),"MISSING",IF(OR(ISNUMBER(FIND(" ",I25)),EXACT(I25,LOWER(I25))=FALSE()),"FIX CASE/SPACE","OK")))
H26: =IF(D26="","",LOWER(SUBSTITUTE(TRIM(D26)&"_"&TRIM(E26)," ","_")&"_"&Inputs!$B$17&"_"&Inputs!$B$18)) | I26: =IF(B26="","",Inputs!$B$16&IF(ISNUMBER(FIND("?",Inputs!$B$16)),"&","?")&"utm_source="&LOWER(B26)&"&utm_medium="&LOWER(C26)&"&utm_campaign="&H26&"&utm_content="&LOWER(SUBSTITUTE(F26," ","_"))&IF(G26="","","&utm_term="&LOWER(SUBSTITUTE(G26," ","_")))) | J26: =IF(B26="","",IF(OR(C26="",D26="",E26="",F26=""),"MISSING",IF(OR(ISNUMBER(FIND(" ",I26)),EXACT(I26,LOWER(I26))=FALSE()),"FIX CASE/SPACE","OK")))
H27: =IF(D27="","",LOWER(SUBSTITUTE(TRIM(D27)&"_"&TRIM(E27)," ","_")&"_"&Inputs!$B$17&"_"&Inputs!$B$18)) | I27: =IF(B27="","",Inputs!$B$16&IF(ISNUMBER(FIND("?",Inputs!$B$16)),"&","?")&"utm_source="&LOWER(B27)&"&utm_medium="&LOWER(C27)&"&utm_campaign="&H27&"&utm_content="&LOWER(SUBSTITUTE(F27," ","_"))&IF(G27="","","&utm_term="&LOWER(SUBSTITUTE(G27," ","_")))) | J27: =IF(B27="","",IF(OR(C27="",D27="",E27="",F27=""),"MISSING",IF(OR(ISNUMBER(FIND(" ",I27)),EXACT(I27,LOWER(I27))=FALSE()),"FIX CASE/SPACE","OK")))
H28: =IF(D28="","",LOWER(SUBSTITUTE(TRIM(D28)&"_"&TRIM(E28)," ","_")&"_"&Inputs!$B$17&"_"&Inputs!$B$18)) | I28: =IF(B28="","",Inputs!$B$16&IF(ISNUMBER(FIND("?",Inputs!$B$16)),"&","?")&"utm_source="&LOWER(B28)&"&utm_medium="&LOWER(C28)&"&utm_campaign="&H28&"&utm_content="&LOWER(SUBSTITUTE(F28," ","_"))&IF(G28="","","&utm_term="&LOWER(SUBSTITUTE(G28," ","_")))) | J28: =IF(B28="","",IF(OR(C28="",D28="",E28="",F28=""),"MISSING",IF(OR(ISNUMBER(FIND(" ",I28)),EXACT(I28,LOWER(I28))=FALSE()),"FIX CASE/SPACE","OK")))
A29: Empty rows at the bottom are ready for new creatives: fill B to G and the link builds itself. Shorten long links with Bitly or TinyURL; the UTMs survive the redirect.

Sheet Tracking Plan
A1: Tracking Plan · GA4 + GTM + platform pixels
A2: What fires where. Built in GTM once, read by every platform. Purchase is the source of truth for ROAS.
A4: Funnel step | B4: GA4 event | C4: Key parameters | D4: GTM trigger | E4: Meta (Pixel + CAPI) | F4: TikTok Pixel | G4: Snap Pixel | H4: Google Ads conversion | I4: Used for
A5: Visit | B5: page_view | C5: page_location, utm_* | D5: All pages | E5: PageView | F5: Pageview | G5: PAGE_VIEW | H5: - | I5: Traffic quality by source/medium
A6: Product interest | B6: view_item | C6: item_id, item_name, value | D6: Product / bundle page view | E6: ViewContent | F6: ViewContent | G6: VIEW_CONTENT | H6: - | I6: Retargeting pool VC 30d (C07)
A7: Planner intent | B7: generate_lead | C7: lead_type = planning_session | D7: Planning-session form submit | E7: Lead | F7: SubmitForm | G7: SIGN_UP | H7: Secondary conversion | I7: MOFU success metric, Entry offer
A8: Cart | B8: add_to_cart | C8: item_id, value, currency=EGP | D8: Add to cart click | E8: AddToCart | F8: AddToCart | G8: ADD_CART | H8: - | I8: Retargeting pool ATC 14d
A9: Checkout | B9: begin_checkout | C9: value, items | D9: Checkout page view | E9: InitiateCheckout | F9: InitiateCheckout | G9: START_CHECKOUT | H9: - | I9: Abandoned-checkout WhatsApp flow
A10: Purchase | B10: purchase | C10: transaction_id, value, currency=EGP, items, coupon | D10: Thank-you page / dataLayer purchase | E10: Purchase (dedup by event_id) | F10: CompletePayment | G10: PURCHASE | H10: Primary conversion (value) | I10: ROAS, CPA, attribution
A12: QA checklist before launch
A13: ☐ | B13: Every ad's destination URL comes from the UTM Builder sheet (no hand-typed UTMs).
A14: ☐ | B14: GA4 DebugView shows purchase with transaction_id and value in EGP on a test order.
A15: ☐ | B15: Meta Pixel and Conversions API send the same event_id so purchases are not double-counted.
A16: ☐ | B16: Google Ads auto-tagging is ON and the GA4 link is active; UTMs go in the Final URL suffix.
A17: ☐ | B17: GA4 custom channel group adds 'WhatsApp' (medium = whatsapp) so it does not land in Unassigned.
A18: ☐ | B18: Cross-domain / payment-gateway domains are added to the GA4 referral exclusion list.
A19: ☐ | B19: Looker Studio report reads GA4 session campaign + platform cost exports, joined on utm_campaign.

Sheet Attribution
A1: Attribution · same conversions, four models
A2: 12 sample conversion paths (illustrative, in the shape of a GA4 Path Exploration export). Weights are formulas, so you can edit any path. | J2: Helper: weight of each touch under each model (do not edit). Time decay doubles the weight at each step closer to purchase (about 7/13/27/53 for 4 touches, close to Session 16's 5/15/30/50).
J3: Last click · T1 | K3: Last click · T2 | L3: Last click · T3 | M3: Last click · T4 | N3: First click · T1 | O3: First click · T2 | P3: First click · T3 | Q3: First click · T4 | R3: Linear · T1 | S3: Linear · T2 | T3: Linear · T3 | U3: Linear · T4 | V3: Time decay · T1 | W3: Time decay · T2 | X3: Time decay · T3 | Y3: Time decay · T4 | Z3: Position-based (40/20/40) · T1 | AA3: Position-based (40/20/40) · T2 | AB3: Position-based (40/20/40) · T3 | AC3: Position-based (40/20/40) · T4
A4: Path # | B4: Touch 1 | C4: Touch 2 | D4: Touch 3 | E4: Touch 4 | F4: Revenue (EGP) | G4: # touches
A5: 1 | B5: TikTok | C5: Meta Prospecting | D5: Google Search | F5: 4800 | G5: =COUNTA(B5:E5) -> 3 | J5: =IF(1=$G5,1,0) -> 0 | K5: =IF(2=$G5,1,0) -> 0 | L5: =IF(3=$G5,1,0) -> 1 | M5: =IF(4=$G5,1,0) -> 0 | N5: =IF(AND(1=1,$G5>=1),1,0) -> 1 | O5: =IF(AND(2=1,$G5>=1),1,0) -> 0 | P5: =IF(AND(3=1,$G5>=1),1,0) -> 0 | Q5: =IF(AND(4=1,$G5>=1),1,0) -> 0 | R5: =IF(1<=$G5,1/$G5,0) -> 0.33333333 | S5: =IF(2<=$G5,1/$G5,0) -> 0.33333333 | T5: =IF(3<=$G5,1/$G5,0) -> 0.33333333 | U5: =IF(4<=$G5,1/$G5,0) -> 0 | V5: =IF(1<=$G5,2^(1-1)/(2^$G5-1),0) -> 0.14285714 | W5: =IF(2<=$G5,2^(2-1)/(2^$G5-1),0) -> 0.28571429 | X5: =IF(3<=$G5,2^(3-1)/(2^$G5-1),0) -> 0.57142857 | Y5: =IF(4<=$G5,2^(4-1)/(2^$G5-1),0) -> 0 | Z5: =IF(1>$G5,0,IF($G5=1,1,IF($G5=2,0.5,IF(OR(1=1,1=$G5),0.4,0.2/($G5-2))))) -> 0.4 | AA5: =IF(2>$G5,0,IF($G5=1,1,IF($G5=2,0.5,IF(OR(2=1,2=$G5),0.4,0.2/($G5-2))))) -> 0.2 | AB5: =IF(3>$G5,0,IF($G5=1,1,IF($G5=2,0.5,IF(OR(3=1,3=$G5),0.4,0.2/($G5-2))))) -> 0.4 | AC5: =IF(4>$G5,0,IF($G5=1,1,IF($G5=2,0.5,IF(OR(4=1,4=$G5),0.4,0.2/($G5-2))))) -> 0
A6: 2 | B6: TikTok | C6: Meta Retargeting | F6: 4200 | G6: =COUNTA(B6:E6) -> 2 | J6: =IF(1=$G6,1,0) -> 0 | K6: =IF(2=$G6,1,0) -> 1 | L6: =IF(3=$G6,1,0) -> 0 | M6: =IF(4=$G6,1,0) -> 0 | N6: =IF(AND(1=1,$G6>=1),1,0) -> 1 | O6: =IF(AND(2=1,$G6>=1),1,0) -> 0 | P6: =IF(AND(3=1,$G6>=1),1,0) -> 0 | Q6: =IF(AND(4=1,$G6>=1),1,0) -> 0 | R6: =IF(1<=$G6,1/$G6,0) -> 0.5 | S6: =IF(2<=$G6,1/$G6,0) -> 0.5 | T6: =IF(3<=$G6,1/$G6,0) -> 0 | U6: =IF(4<=$G6,1/$G6,0) -> 0 | V6: =IF(1<=$G6,2^(1-1)/(2^$G6-1),0) -> 0.33333333 | W6: =IF(2<=$G6,2^(2-1)/(2^$G6-1),0) -> 0.66666667 | X6: =IF(3<=$G6,2^(3-1)/(2^$G6-1),0) -> 0 | Y6: =IF(4<=$G6,2^(4-1)/(2^$G6-1),0) -> 0 | Z6: =IF(1>$G6,0,IF($G6=1,1,IF($G6=2,0.5,IF(OR(1=1,1=$G6),0.4,0.2/($G6-2))))) -> 0.5 | AA6: =IF(2>$G6,0,IF($G6=1,1,IF($G6=2,0.5,IF(OR(2=1,2=$G6),0.4,0.2/($G6-2))))) -> 0.5 | AB6: =IF(3>$G6,0,IF($G6=1,1,IF($G6=2,0.5,IF(OR(3=1,3=$G6),0.4,0.2/($G6-2))))) -> 0 | AC6: =IF(4>$G6,0,IF($G6=1,1,IF($G6=2,0.5,IF(OR(4=1,4=$G6),0.4,0.2/($G6-2))))) -> 0
A7: 3 | B7: Google Search | F7: 3900 | G7: =COUNTA(B7:E7) -> 1 | J7: =IF(1=$G7,1,0) -> 1 | K7: =IF(2=$G7,1,0) -> 0 | L7: =IF(3=$G7,1,0) -> 0 | M7: =IF(4=$G7,1,0) -> 0 | N7: =IF(AND(1=1,$G7>=1),1,0) -> 1 | O7: =IF(AND(2=1,$G7>=1),1,0) -> 0 | P7: =IF(AND(3=1,$G7>=1),1,0) -> 0 | Q7: =IF(AND(4=1,$G7>=1),1,0) -> 0 | R7: =IF(1<=$G7,1/$G7,0) -> 1 | S7: =IF(2<=$G7,1/$G7,0) -> 0 | T7: =IF(3<=$G7,1/$G7,0) -> 0 | U7: =IF(4<=$G7,1/$G7,0) -> 0 | V7: =IF(1<=$G7,2^(1-1)/(2^$G7-1),0) -> 1 | W7: =IF(2<=$G7,2^(2-1)/(2^$G7-1),0) -> 0 | X7: =IF(3<=$G7,2^(3-1)/(2^$G7-1),0) -> 0 | Y7: =IF(4<=$G7,2^(4-1)/(2^$G7-1),0) -> 0 | Z7: =IF(1>$G7,0,IF($G7=1,1,IF($G7=2,0.5,IF(OR(1=1,1=$G7),0.4,0.2/($G7-2))))) -> 1 | AA7: =IF(2>$G7,0,IF($G7=1,1,IF($G7=2,0.5,IF(OR(2=1,2=$G7),0.4,0.2/($G7-2))))) -> 0 | AB7: =IF(3>$G7,0,IF($G7=1,1,IF($G7=2,0.5,IF(OR(3=1,3=$G7),0.4,0.2/($G7-2))))) -> 0 | AC7: =IF(4>$G7,0,IF($G7=1,1,IF($G7=2,0.5,IF(OR(4=1,4=$G7),0.4,0.2/($G7-2))))) -> 0
A8: 4 | B8: TikTok | C8: Google Search | D8: Email/WhatsApp | F8: 5600 | G8: =COUNTA(B8:E8) -> 3 | J8: =IF(1=$G8,1,0) -> 0 | K8: =IF(2=$G8,1,0) -> 0 | L8: =IF(3=$G8,1,0) -> 1 | M8: =IF(4=$G8,1,0) -> 0 | N8: =IF(AND(1=1,$G8>=1),1,0) -> 1 | O8: =IF(AND(2=1,$G8>=1),1,0) -> 0 | P8: =IF(AND(3=1,$G8>=1),1,0) -> 0 | Q8: =IF(AND(4=1,$G8>=1),1,0) -> 0 | R8: =IF(1<=$G8,1/$G8,0) -> 0.33333333 | S8: =IF(2<=$G8,1/$G8,0) -> 0.33333333 | T8: =IF(3<=$G8,1/$G8,0) -> 0.33333333 | U8: =IF(4<=$G8,1/$G8,0) -> 0 | V8: =IF(1<=$G8,2^(1-1)/(2^$G8-1),0) -> 0.14285714 | W8: =IF(2<=$G8,2^(2-1)/(2^$G8-1),0) -> 0.28571429 | X8: =IF(3<=$G8,2^(3-1)/(2^$G8-1),0) -> 0.57142857 | Y8: =IF(4<=$G8,2^(4-1)/(2^$G8-1),0) -> 0 | Z8: =IF(1>$G8,0,IF($G8=1,1,IF($G8=2,0.5,IF(OR(1=1,1=$G8),0.4,0.2/($G8-2))))) -> 0.4 | AA8: =IF(2>$G8,0,IF($G8=1,1,IF($G8=2,0.5,IF(OR(2=1,2=$G8),0.4,0.2/($G8-2))))) -> 0.2 | AB8: =IF(3>$G8,0,IF($G8=1,1,IF($G8=2,0.5,IF(OR(3=1,3=$G8),0.4,0.2/($G8-2))))) -> 0.4 | AC8: =IF(4>$G8,0,IF($G8=1,1,IF($G8=2,0.5,IF(OR(4=1,4=$G8),0.4,0.2/($G8-2))))) -> 0
A9: 5 | B9: Meta Prospecting | C9: Meta Retargeting | D9: Google Search | F9: 4500 | G9: =COUNTA(B9:E9) -> 3 | J9: =IF(1=$G9,1,0) -> 0 | K9: =IF(2=$G9,1,0) -> 0 | L9: =IF(3=$G9,1,0) -> 1 | M9: =IF(4=$G9,1,0) -> 0 | N9: =IF(AND(1=1,$G9>=1),1,0) -> 1 | O9: =IF(AND(2=1,$G9>=1),1,0) -> 0 | P9: =IF(AND(3=1,$G9>=1),1,0) -> 0 | Q9: =IF(AND(4=1,$G9>=1),1,0) -> 0 | R9: =IF(1<=$G9,1/$G9,0) -> 0.33333333 | S9: =IF(2<=$G9,1/$G9,0) -> 0.33333333 | T9: =IF(3<=$G9,1/$G9,0) -> 0.33333333 | U9: =IF(4<=$G9,1/$G9,0) -> 0 | V9: =IF(1<=$G9,2^(1-1)/(2^$G9-1),0) -> 0.14285714 | W9: =IF(2<=$G9,2^(2-1)/(2^$G9-1),0) -> 0.28571429 | X9: =IF(3<=$G9,2^(3-1)/(2^$G9-1),0) -> 0.57142857 | Y9: =IF(4<=$G9,2^(4-1)/(2^$G9-1),0) -> 0 | Z9: =IF(1>$G9,0,IF($G9=1,1,IF($G9=2,0.5,IF(OR(1=1,1=$G9),0.4,0.2/($G9-2))))) -> 0.4 | AA9: =IF(2>$G9,0,IF($G9=1,1,IF($G9=2,0.5,IF(OR(2=1,2=$G9),0.4,0.2/($G9-2))))) -> 0.2 | AB9: =IF(3>$G9,0,IF($G9=1,1,IF($G9=2,0.5,IF(OR(3=1,3=$G9),0.4,0.2/($G9-2))))) -> 0.4 | AC9: =IF(4>$G9,0,IF($G9=1,1,IF($G9=2,0.5,IF(OR(4=1,4=$G9),0.4,0.2/($G9-2))))) -> 0
A10: 6 | B10: YouTube | C10: Google PMax | F10: 4100 | G10: =COUNTA(B10:E10) -> 2 | J10: =IF(1=$G10,1,0) -> 0 | K10: =IF(2=$G10,1,0) -> 1 | L10: =IF(3=$G10,1,0) -> 0 | M10: =IF(4=$G10,1,0) -> 0 | N10: =IF(AND(1=1,$G10>=1),1,0) -> 1 | O10: =IF(AND(2=1,$G10>=1),1,0) -> 0 | P10: =IF(AND(3=1,$G10>=1),1,0) -> 0 | Q10: =IF(AND(4=1,$G10>=1),1,0) -> 0 | R10: =IF(1<=$G10,1/$G10,0) -> 0.5 | S10: =IF(2<=$G10,1/$G10,0) -> 0.5 | T10: =IF(3<=$G10,1/$G10,0) -> 0 | U10: =IF(4<=$G10,1/$G10,0) -> 0 | V10: =IF(1<=$G10,2^(1-1)/(2^$G10-1),0) -> 0.33333333 | W10: =IF(2<=$G10,2^(2-1)/(2^$G10-1),0) -> 0.66666667 | X10: =IF(3<=$G10,2^(3-1)/(2^$G10-1),0) -> 0 | Y10: =IF(4<=$G10,2^(4-1)/(2^$G10-1),0) -> 0 | Z10: =IF(1>$G10,0,IF($G10=1,1,IF($G10=2,0.5,IF(OR(1=1,1=$G10),0.4,0.2/($G10-2))))) -> 0.5 | AA10: =IF(2>$G10,0,IF($G10=1,1,IF($G10=2,0.5,IF(OR(2=1,2=$G10),0.4,0.2/($G10-2))))) -> 0.5 | AB10: =IF(3>$G10,0,IF($G10=1,1,IF($G10=2,0.5,IF(OR(3=1,3=$G10),0.4,0.2/($G10-2))))) -> 0 | AC10: =IF(4>$G10,0,IF($G10=1,1,IF($G10=2,0.5,IF(OR(4=1,4=$G10),0.4,0.2/($G10-2))))) -> 0
A11: 7 | B11: TikTok | C11: Meta Prospecting | D11: Meta Retargeting | E11: Google Search | F11: 6200 | G11: =COUNTA(B11:E11) -> 4 | J11: =IF(1=$G11,1,0) -> 0 | K11: =IF(2=$G11,1,0) -> 0 | L11: =IF(3=$G11,1,0) -> 0 | M11: =IF(4=$G11,1,0) -> 1 | N11: =IF(AND(1=1,$G11>=1),1,0) -> 1 | O11: =IF(AND(2=1,$G11>=1),1,0) -> 0 | P11: =IF(AND(3=1,$G11>=1),1,0) -> 0 | Q11: =IF(AND(4=1,$G11>=1),1,0) -> 0 | R11: =IF(1<=$G11,1/$G11,0) -> 0.25 | S11: =IF(2<=$G11,1/$G11,0) -> 0.25 | T11: =IF(3<=$G11,1/$G11,0) -> 0.25 | U11: =IF(4<=$G11,1/$G11,0) -> 0.25 | V11: =IF(1<=$G11,2^(1-1)/(2^$G11-1),0) -> 0.066666667 | W11: =IF(2<=$G11,2^(2-1)/(2^$G11-1),0) -> 0.13333333 | X11: =IF(3<=$G11,2^(3-1)/(2^$G11-1),0) -> 0.26666667 | Y11: =IF(4<=$G11,2^(4-1)/(2^$G11-1),0) -> 0.53333333 | Z11: =IF(1>$G11,0,IF($G11=1,1,IF($G11=2,0.5,IF(OR(1=1,1=$G11),0.4,0.2/($G11-2))))) -> 0.4 | AA11: =IF(2>$G11,0,IF($G11=1,1,IF($G11=2,0.5,IF(OR(2=1,2=$G11),0.4,0.2/($G11-2))))) -> 0.1 | AB11: =IF(3>$G11,0,IF($G11=1,1,IF($G11=2,0.5,IF(OR(3=1,3=$G11),0.4,0.2/($G11-2))))) -> 0.1 | AC11: =IF(4>$G11,0,IF($G11=1,1,IF($G11=2,0.5,IF(OR(4=1,4=$G11),0.4,0.2/($G11-2))))) -> 0.4
A12: 8 | B12: Snapchat | C12: Meta Retargeting | F12: 3700 | G12: =COUNTA(B12:E12) -> 2 | J12: =IF(1=$G12,1,0) -> 0 | K12: =IF(2=$G12,1,0) -> 1 | L12: =IF(3=$G12,1,0) -> 0 | M12: =IF(4=$G12,1,0) -> 0 | N12: =IF(AND(1=1,$G12>=1),1,0) -> 1 | O12: =IF(AND(2=1,$G12>=1),1,0) -> 0 | P12: =IF(AND(3=1,$G12>=1),1,0) -> 0 | Q12: =IF(AND(4=1,$G12>=1),1,0) -> 0 | R12: =IF(1<=$G12,1/$G12,0) -> 0.5 | S12: =IF(2<=$G12,1/$G12,0) -> 0.5 | T12: =IF(3<=$G12,1/$G12,0) -> 0 | U12: =IF(4<=$G12,1/$G12,0) -> 0 | V12: =IF(1<=$G12,2^(1-1)/(2^$G12-1),0) -> 0.33333333 | W12: =IF(2<=$G12,2^(2-1)/(2^$G12-1),0) -> 0.66666667 | X12: =IF(3<=$G12,2^(3-1)/(2^$G12-1),0) -> 0 | Y12: =IF(4<=$G12,2^(4-1)/(2^$G12-1),0) -> 0 | Z12: =IF(1>$G12,0,IF($G12=1,1,IF($G12=2,0.5,IF(OR(1=1,1=$G12),0.4,0.2/($G12-2))))) -> 0.5 | AA12: =IF(2>$G12,0,IF($G12=1,1,IF($G12=2,0.5,IF(OR(2=1,2=$G12),0.4,0.2/($G12-2))))) -> 0.5 | AB12: =IF(3>$G12,0,IF($G12=1,1,IF($G12=2,0.5,IF(OR(3=1,3=$G12),0.4,0.2/($G12-2))))) -> 0 | AC12: =IF(4>$G12,0,IF($G12=1,1,IF($G12=2,0.5,IF(OR(4=1,4=$G12),0.4,0.2/($G12-2))))) -> 0
A13: 9 | B13: Google PMax | F13: 4400 | G13: =COUNTA(B13:E13) -> 1 | J13: =IF(1=$G13,1,0) -> 1 | K13: =IF(2=$G13,1,0) -> 0 | L13: =IF(3=$G13,1,0) -> 0 | M13: =IF(4=$G13,1,0) -> 0 | N13: =IF(AND(1=1,$G13>=1),1,0) -> 1 | O13: =IF(AND(2=1,$G13>=1),1,0) -> 0 | P13: =IF(AND(3=1,$G13>=1),1,0) -> 0 | Q13: =IF(AND(4=1,$G13>=1),1,0) -> 0 | R13: =IF(1<=$G13,1/$G13,0) -> 1 | S13: =IF(2<=$G13,1/$G13,0) -> 0 | T13: =IF(3<=$G13,1/$G13,0) -> 0 | U13: =IF(4<=$G13,1/$G13,0) -> 0 | V13: =IF(1<=$G13,2^(1-1)/(2^$G13-1),0) -> 1 | W13: =IF(2<=$G13,2^(2-1)/(2^$G13-1),0) -> 0 | X13: =IF(3<=$G13,2^(3-1)/(2^$G13-1),0) -> 0 | Y13: =IF(4<=$G13,2^(4-1)/(2^$G13-1),0) -> 0 | Z13: =IF(1>$G13,0,IF($G13=1,1,IF($G13=2,0.5,IF(OR(1=1,1=$G13),0.4,0.2/($G13-2))))) -> 1 | AA13: =IF(2>$G13,0,IF($G13=1,1,IF($G13=2,0.5,IF(OR(2=1,2=$G13),0.4,0.2/($G13-2))))) -> 0 | AB13: =IF(3>$G13,0,IF($G13=1,1,IF($G13=2,0.5,IF(OR(3=1,3=$G13),0.4,0.2/($G13-2))))) -> 0 | AC13: =IF(4>$G13,0,IF($G13=1,1,IF($G13=2,0.5,IF(OR(4=1,4=$G13),0.4,0.2/($G13-2))))) -> 0
A14: 10 | B14: TikTok | C14: Google PMax | D14: Email/WhatsApp | F14: 5100 | G14: =COUNTA(B14:E14) -> 3 | J14: =IF(1=$G14,1,0) -> 0 | K14: =IF(2=$G14,1,0) -> 0 | L14: =IF(3=$G14,1,0) -> 1 | M14: =IF(4=$G14,1,0) -> 0 | N14: =IF(AND(1=1,$G14>=1),1,0) -> 1 | O14: =IF(AND(2=1,$G14>=1),1,0) -> 0 | P14: =IF(AND(3=1,$G14>=1),1,0) -> 0 | Q14: =IF(AND(4=1,$G14>=1),1,0) -> 0 | R14: =IF(1<=$G14,1/$G14,0) -> 0.33333333 | S14: =IF(2<=$G14,1/$G14,0) -> 0.33333333 | T14: =IF(3<=$G14,1/$G14,0) -> 0.33333333 | U14: =IF(4<=$G14,1/$G14,0) -> 0 | V14: =IF(1<=$G14,2^(1-1)/(2^$G14-1),0) -> 0.14285714 | W14: =IF(2<=$G14,2^(2-1)/(2^$G14-1),0) -> 0.28571429 | X14: =IF(3<=$G14,2^(3-1)/(2^$G14-1),0) -> 0.57142857 | Y14: =IF(4<=$G14,2^(4-1)/(2^$G14-1),0) -> 0 | Z14: =IF(1>$G14,0,IF($G14=1,1,IF($G14=2,0.5,IF(OR(1=1,1=$G14),0.4,0.2/($G14-2))))) -> 0.4 | AA14: =IF(2>$G14,0,IF($G14=1,1,IF($G14=2,0.5,IF(OR(2=1,2=$G14),0.4,0.2/($G14-2))))) -> 0.2 | AB14: =IF(3>$G14,0,IF($G14=1,1,IF($G14=2,0.5,IF(OR(3=1,3=$G14),0.4,0.2/($G14-2))))) -> 0.4 | AC14: =IF(4>$G14,0,IF($G14=1,1,IF($G14=2,0.5,IF(OR(4=1,4=$G14),0.4,0.2/($G14-2))))) -> 0
A15: 11 | B15: Meta Prospecting | C15: Google Search | F15: 4000 | G15: =COUNTA(B15:E15) -> 2 | J15: =IF(1=$G15,1,0) -> 0 | K15: =IF(2=$G15,1,0) -> 1 | L15: =IF(3=$G15,1,0) -> 0 | M15: =IF(4=$G15,1,0) -> 0 | N15: =IF(AND(1=1,$G15>=1),1,0) -> 1 | O15: =IF(AND(2=1,$G15>=1),1,0) -> 0 | P15: =IF(AND(3=1,$G15>=1),1,0) -> 0 | Q15: =IF(AND(4=1,$G15>=1),1,0) -> 0 | R15: =IF(1<=$G15,1/$G15,0) -> 0.5 | S15: =IF(2<=$G15,1/$G15,0) -> 0.5 | T15: =IF(3<=$G15,1/$G15,0) -> 0 | U15: =IF(4<=$G15,1/$G15,0) -> 0 | V15: =IF(1<=$G15,2^(1-1)/(2^$G15-1),0) -> 0.33333333 | W15: =IF(2<=$G15,2^(2-1)/(2^$G15-1),0) -> 0.66666667 | X15: =IF(3<=$G15,2^(3-1)/(2^$G15-1),0) -> 0 | Y15: =IF(4<=$G15,2^(4-1)/(2^$G15-1),0) -> 0 | Z15: =IF(1>$G15,0,IF($G15=1,1,IF($G15=2,0.5,IF(OR(1=1,1=$G15),0.4,0.2/($G15-2))))) -> 0.5 | AA15: =IF(2>$G15,0,IF($G15=1,1,IF($G15=2,0.5,IF(OR(2=1,2=$G15),0.4,0.2/($G15-2))))) -> 0.5 | AB15: =IF(3>$G15,0,IF($G15=1,1,IF($G15=2,0.5,IF(OR(3=1,3=$G15),0.4,0.2/($G15-2))))) -> 0 | AC15: =IF(4>$G15,0,IF($G15=1,1,IF($G15=2,0.5,IF(OR(4=1,4=$G15),0.4,0.2/($G15-2))))) -> 0
A16: 12 | B16: Email/WhatsApp | F16: 4600 | G16: =COUNTA(B16:E16) -> 1 | J16: =IF(1=$G16,1,0) -> 1 | K16: =IF(2=$G16,1,0) -> 0 | L16: =IF(3=$G16,1,0) -> 0 | M16: =IF(4=$G16,1,0) -> 0 | N16: =IF(AND(1=1,$G16>=1),1,0) -> 1 | O16: =IF(AND(2=1,$G16>=1),1,0) -> 0 | P16: =IF(AND(3=1,$G16>=1),1,0) -> 0 | Q16: =IF(AND(4=1,$G16>=1),1,0) -> 0 | R16: =IF(1<=$G16,1/$G16,0) -> 1 | S16: =IF(2<=$G16,1/$G16,0) -> 0 | T16: =IF(3<=$G16,1/$G16,0) -> 0 | U16: =IF(4<=$G16,1/$G16,0) -> 0 | V16: =IF(1<=$G16,2^(1-1)/(2^$G16-1),0) -> 1 | W16: =IF(2<=$G16,2^(2-1)/(2^$G16-1),0) -> 0 | X16: =IF(3<=$G16,2^(3-1)/(2^$G16-1),0) -> 0 | Y16: =IF(4<=$G16,2^(4-1)/(2^$G16-1),0) -> 0 | Z16: =IF(1>$G16,0,IF($G16=1,1,IF($G16=2,0.5,IF(OR(1=1,1=$G16),0.4,0.2/($G16-2))))) -> 1 | AA16: =IF(2>$G16,0,IF($G16=1,1,IF($G16=2,0.5,IF(OR(2=1,2=$G16),0.4,0.2/($G16-2))))) -> 0 | AB16: =IF(3>$G16,0,IF($G16=1,1,IF($G16=2,0.5,IF(OR(3=1,3=$G16),0.4,0.2/($G16-2))))) -> 0 | AC16: =IF(4>$G16,0,IF($G16=1,1,IF($G16=2,0.5,IF(OR(4=1,4=$G16),0.4,0.2/($G16-2))))) -> 0
E17: Total | F17: =SUM(F5:F16) -> 55100
A19: Revenue credit by channel (EGP)
A20: Channel | B20: Last click | C20: First click | D20: Linear | E20: Time decay | F20: Position-based (40/20/40) | G20: Shift: last click to position-based | H20: Position-based share
A21: TikTok | B21: =SUMPRODUCT((B$5:B$16=$A21)*J$5:J$16*$F$5:$F$16)+SUMPRODUCT((C$5:C$16=$A21)*K$5:K$16*$F$5:$F$16)+SUMPRODUCT((D$5:D$16=$A21)*L$5:L$16*$F$5:$F$16)+SUMPRODUCT((E$5:E$16=$A21)*M$5:M$16*$F$5:$F$16) -> 0 | C21: =SUMPRODUCT((B$5:B$16=$A21)*N$5:N$16*$F$5:$F$16)+SUMPRODUCT((C$5:C$16=$A21)*O$5:O$16*$F$5:$F$16)+SUMPRODUCT((D$5:D$16=$A21)*P$5:P$16*$F$5:$F$16)+SUMPRODUCT((E$5:E$16=$A21)*Q$5:Q$16*$F$5:$F$16) -> 25900 | D21: =SUMPRODUCT((B$5:B$16=$A21)*R$5:R$16*$F$5:$F$16)+SUMPRODUCT((C$5:C$16=$A21)*S$5:S$16*$F$5:$F$16)+SUMPRODUCT((D$5:D$16=$A21)*T$5:T$16*$F$5:$F$16)+SUMPRODUCT((E$5:E$16=$A21)*U$5:U$16*$F$5:$F$16) -> 8816.6667 | E21: =SUMPRODUCT((B$5:B$16=$A21)*V$5:V$16*$F$5:$F$16)+SUMPRODUCT((C$5:C$16=$A21)*W$5:W$16*$F$5:$F$16)+SUMPRODUCT((D$5:D$16=$A21)*X$5:X$16*$F$5:$F$16)+SUMPRODUCT((E$5:E$16=$A21)*Y$5:Y$16*$F$5:$F$16) -> 4027.619 | F21: =SUMPRODUCT((B$5:B$16=$A21)*Z$5:Z$16*$F$5:$F$16)+SUMPRODUCT((C$5:C$16=$A21)*AA$5:AA$16*$F$5:$F$16)+SUMPRODUCT((D$5:D$16=$A21)*AB$5:AB$16*$F$5:$F$16)+SUMPRODUCT((E$5:E$16=$A21)*AC$5:AC$16*$F$5:$F$16) -> 10780 | G21: =F21-B21 -> 10780 | H21: =F21/$F$29 -> 0.19564428
A22: YouTube | B22: =SUMPRODUCT((B$5:B$16=$A22)*J$5:J$16*$F$5:$F$16)+SUMPRODUCT((C$5:C$16=$A22)*K$5:K$16*$F$5:$F$16)+SUMPRODUCT((D$5:D$16=$A22)*L$5:L$16*$F$5:$F$16)+SUMPRODUCT((E$5:E$16=$A22)*M$5:M$16*$F$5:$F$16) -> 0 | C22: =SUMPRODUCT((B$5:B$16=$A22)*N$5:N$16*$F$5:$F$16)+SUMPRODUCT((C$5:C$16=$A22)*O$5:O$16*$F$5:$F$16)+SUMPRODUCT((D$5:D$16=$A22)*P$5:P$16*$F$5:$F$16)+SUMPRODUCT((E$5:E$16=$A22)*Q$5:Q$16*$F$5:$F$16) -> 4100 | D22: =SUMPRODUCT((B$5:B$16=$A22)*R$5:R$16*$F$5:$F$16)+SUMPRODUCT((C$5:C$16=$A22)*S$5:S$16*$F$5:$F$16)+SUMPRODUCT((D$5:D$16=$A22)*T$5:T$16*$F$5:$F$16)+SUMPRODUCT((E$5:E$16=$A22)*U$5:U$16*$F$5:$F$16) -> 2050 | E22: =SUMPRODUCT((B$5:B$16=$A22)*V$5:V$16*$F$5:$F$16)+SUMPRODUCT((C$5:C$16=$A22)*W$5:W$16*$F$5:$F$16)+SUMPRODUCT((D$5:D$16=$A22)*X$5:X$16*$F$5:$F$16)+SUMPRODUCT((E$5:E$16=$A22)*Y$5:Y$16*$F$5:$F$16) -> 1366.6667 | F22: =SUMPRODUCT((B$5:B$16=$A22)*Z$5:Z$16*$F$5:$F$16)+SUMPRODUCT((C$5:C$16=$A22)*AA$5:AA$16*$F$5:$F$16)+SUMPRODUCT((D$5:D$16=$A22)*AB$5:AB$16*$F$5:$F$16)+SUMPRODUCT((E$5:E$16=$A22)*AC$5:AC$16*$F$5:$F$16) -> 2050 | G22: =F22-B22 -> 2050 | H22: =F22/$F$29 -> 0.037205082
A23: Snapchat | B23: =SUMPRODUCT((B$5:B$16=$A23)*J$5:J$16*$F$5:$F$16)+SUMPRODUCT((C$5:C$16=$A23)*K$5:K$16*$F$5:$F$16)+SUMPRODUCT((D$5:D$16=$A23)*L$5:L$16*$F$5:$F$16)+SUMPRODUCT((E$5:E$16=$A23)*M$5:M$16*$F$5:$F$16) -> 0 | C23: =SUMPRODUCT((B$5:B$16=$A23)*N$5:N$16*$F$5:$F$16)+SUMPRODUCT((C$5:C$16=$A23)*O$5:O$16*$F$5:$F$16)+SUMPRODUCT((D$5:D$16=$A23)*P$5:P$16*$F$5:$F$16)+SUMPRODUCT((E$5:E$16=$A23)*Q$5:Q$16*$F$5:$F$16) -> 3700 | D23: =SUMPRODUCT((B$5:B$16=$A23)*R$5:R$16*$F$5:$F$16)+SUMPRODUCT((C$5:C$16=$A23)*S$5:S$16*$F$5:$F$16)+SUMPRODUCT((D$5:D$16=$A23)*T$5:T$16*$F$5:$F$16)+SUMPRODUCT((E$5:E$16=$A23)*U$5:U$16*$F$5:$F$16) -> 1850 | E23: =SUMPRODUCT((B$5:B$16=$A23)*V$5:V$16*$F$5:$F$16)+SUMPRODUCT((C$5:C$16=$A23)*W$5:W$16*$F$5:$F$16)+SUMPRODUCT((D$5:D$16=$A23)*X$5:X$16*$F$5:$F$16)+SUMPRODUCT((E$5:E$16=$A23)*Y$5:Y$16*$F$5:$F$16) -> 1233.3333 | F23: =SUMPRODUCT((B$5:B$16=$A23)*Z$5:Z$16*$F$5:$F$16)+SUMPRODUCT((C$5:C$16=$A23)*AA$5:AA$16*$F$5:$F$16)+SUMPRODUCT((D$5:D$16=$A23)*AB$5:AB$16*$F$5:$F$16)+SUMPRODUCT((E$5:E$16=$A23)*AC$5:AC$16*$F$5:$F$16) -> 1850 | G23: =F23-B23 -> 1850 | H23: =F23/$F$29 -> 0.033575318
A24: Meta Prospecting | B24: =SUMPRODUCT((B$5:B$16=$A24)*J$5:J$16*$F$5:$F$16)+SUMPRODUCT((C$5:C$16=$A24)*K$5:K$16*$F$5:$F$16)+SUMPRODUCT((D$5:D$16=$A24)*L$5:L$16*$F$5:$F$16)+SUMPRODUCT((E$5:E$16=$A24)*M$5:M$16*$F$5:$F$16) -> 0 | C24: =SUMPRODUCT((B$5:B$16=$A24)*N$5:N$16*$F$5:$F$16)+SUMPRODUCT((C$5:C$16=$A24)*O$5:O$16*$F$5:$F$16)+SUMPRODUCT((D$5:D$16=$A24)*P$5:P$16*$F$5:$F$16)+SUMPRODUCT((E$5:E$16=$A24)*Q$5:Q$16*$F$5:$F$16) -> 8500 | D24: =SUMPRODUCT((B$5:B$16=$A24)*R$5:R$16*$F$5:$F$16)+SUMPRODUCT((C$5:C$16=$A24)*S$5:S$16*$F$5:$F$16)+SUMPRODUCT((D$5:D$16=$A24)*T$5:T$16*$F$5:$F$16)+SUMPRODUCT((E$5:E$16=$A24)*U$5:U$16*$F$5:$F$16) -> 6650 | E24: =SUMPRODUCT((B$5:B$16=$A24)*V$5:V$16*$F$5:$F$16)+SUMPRODUCT((C$5:C$16=$A24)*W$5:W$16*$F$5:$F$16)+SUMPRODUCT((D$5:D$16=$A24)*X$5:X$16*$F$5:$F$16)+SUMPRODUCT((E$5:E$16=$A24)*Y$5:Y$16*$F$5:$F$16) -> 4174.2857 | F24: =SUMPRODUCT((B$5:B$16=$A24)*Z$5:Z$16*$F$5:$F$16)+SUMPRODUCT((C$5:C$16=$A24)*AA$5:AA$16*$F$5:$F$16)+SUMPRODUCT((D$5:D$16=$A24)*AB$5:AB$16*$F$5:$F$16)+SUMPRODUCT((E$5:E$16=$A24)*AC$5:AC$16*$F$5:$F$16) -> 5380 | G24: =F24-B24 -> 5380 | H24: =F24/$F$29 -> 0.097640653
A25: Meta Retargeting | B25: =SUMPRODUCT((B$5:B$16=$A25)*J$5:J$16*$F$5:$F$16)+SUMPRODUCT((C$5:C$16=$A25)*K$5:K$16*$F$5:$F$16)+SUMPRODUCT((D$5:D$16=$A25)*L$5:L$16*$F$5:$F$16)+SUMPRODUCT((E$5:E$16=$A25)*M$5:M$16*$F$5:$F$16) -> 7900 | C25: =SUMPRODUCT((B$5:B$16=$A25)*N$5:N$16*$F$5:$F$16)+SUMPRODUCT((C$5:C$16=$A25)*O$5:O$16*$F$5:$F$16)+SUMPRODUCT((D$5:D$16=$A25)*P$5:P$16*$F$5:$F$16)+SUMPRODUCT((E$5:E$16=$A25)*Q$5:Q$16*$F$5:$F$16) -> 0 | D25: =SUMPRODUCT((B$5:B$16=$A25)*R$5:R$16*$F$5:$F$16)+SUMPRODUCT((C$5:C$16=$A25)*S$5:S$16*$F$5:$F$16)+SUMPRODUCT((D$5:D$16=$A25)*T$5:T$16*$F$5:$F$16)+SUMPRODUCT((E$5:E$16=$A25)*U$5:U$16*$F$5:$F$16) -> 7000 | E25: =SUMPRODUCT((B$5:B$16=$A25)*V$5:V$16*$F$5:$F$16)+SUMPRODUCT((C$5:C$16=$A25)*W$5:W$16*$F$5:$F$16)+SUMPRODUCT((D$5:D$16=$A25)*X$5:X$16*$F$5:$F$16)+SUMPRODUCT((E$5:E$16=$A25)*Y$5:Y$16*$F$5:$F$16) -> 8205.7143 | F25: =SUMPRODUCT((B$5:B$16=$A25)*Z$5:Z$16*$F$5:$F$16)+SUMPRODUCT((C$5:C$16=$A25)*AA$5:AA$16*$F$5:$F$16)+SUMPRODUCT((D$5:D$16=$A25)*AB$5:AB$16*$F$5:$F$16)+SUMPRODUCT((E$5:E$16=$A25)*AC$5:AC$16*$F$5:$F$16) -> 5470 | G25: =F25-B25 -> -2430 | H25: =F25/$F$29 -> 0.099274047
A26: Google Search | B26: =SUMPRODUCT((B$5:B$16=$A26)*J$5:J$16*$F$5:$F$16)+SUMPRODUCT((C$5:C$16=$A26)*K$5:K$16*$F$5:$F$16)+SUMPRODUCT((D$5:D$16=$A26)*L$5:L$16*$F$5:$F$16)+SUMPRODUCT((E$5:E$16=$A26)*M$5:M$16*$F$5:$F$16) -> 23400 | C26: =SUMPRODUCT((B$5:B$16=$A26)*N$5:N$16*$F$5:$F$16)+SUMPRODUCT((C$5:C$16=$A26)*O$5:O$16*$F$5:$F$16)+SUMPRODUCT((D$5:D$16=$A26)*P$5:P$16*$F$5:$F$16)+SUMPRODUCT((E$5:E$16=$A26)*Q$5:Q$16*$F$5:$F$16) -> 3900 | D26: =SUMPRODUCT((B$5:B$16=$A26)*R$5:R$16*$F$5:$F$16)+SUMPRODUCT((C$5:C$16=$A26)*S$5:S$16*$F$5:$F$16)+SUMPRODUCT((D$5:D$16=$A26)*T$5:T$16*$F$5:$F$16)+SUMPRODUCT((E$5:E$16=$A26)*U$5:U$16*$F$5:$F$16) -> 12416.667 | E26: =SUMPRODUCT((B$5:B$16=$A26)*V$5:V$16*$F$5:$F$16)+SUMPRODUCT((C$5:C$16=$A26)*W$5:W$16*$F$5:$F$16)+SUMPRODUCT((D$5:D$16=$A26)*X$5:X$16*$F$5:$F$16)+SUMPRODUCT((E$5:E$16=$A26)*Y$5:Y$16*$F$5:$F$16) -> 16787.619 | F26: =SUMPRODUCT((B$5:B$16=$A26)*Z$5:Z$16*$F$5:$F$16)+SUMPRODUCT((C$5:C$16=$A26)*AA$5:AA$16*$F$5:$F$16)+SUMPRODUCT((D$5:D$16=$A26)*AB$5:AB$16*$F$5:$F$16)+SUMPRODUCT((E$5:E$16=$A26)*AC$5:AC$16*$F$5:$F$16) -> 13220 | G26: =F26-B26 -> -10180 | H26: =F26/$F$29 -> 0.2399274
A27: Google PMax | B27: =SUMPRODUCT((B$5:B$16=$A27)*J$5:J$16*$F$5:$F$16)+SUMPRODUCT((C$5:C$16=$A27)*K$5:K$16*$F$5:$F$16)+SUMPRODUCT((D$5:D$16=$A27)*L$5:L$16*$F$5:$F$16)+SUMPRODUCT((E$5:E$16=$A27)*M$5:M$16*$F$5:$F$16) -> 8500 | C27: =SUMPRODUCT((B$5:B$16=$A27)*N$5:N$16*$F$5:$F$16)+SUMPRODUCT((C$5:C$16=$A27)*O$5:O$16*$F$5:$F$16)+SUMPRODUCT((D$5:D$16=$A27)*P$5:P$16*$F$5:$F$16)+SUMPRODUCT((E$5:E$16=$A27)*Q$5:Q$16*$F$5:$F$16) -> 4400 | D27: =SUMPRODUCT((B$5:B$16=$A27)*R$5:R$16*$F$5:$F$16)+SUMPRODUCT((C$5:C$16=$A27)*S$5:S$16*$F$5:$F$16)+SUMPRODUCT((D$5:D$16=$A27)*T$5:T$16*$F$5:$F$16)+SUMPRODUCT((E$5:E$16=$A27)*U$5:U$16*$F$5:$F$16) -> 8150 | E27: =SUMPRODUCT((B$5:B$16=$A27)*V$5:V$16*$F$5:$F$16)+SUMPRODUCT((C$5:C$16=$A27)*W$5:W$16*$F$5:$F$16)+SUMPRODUCT((D$5:D$16=$A27)*X$5:X$16*$F$5:$F$16)+SUMPRODUCT((E$5:E$16=$A27)*Y$5:Y$16*$F$5:$F$16) -> 8590.4762 | F27: =SUMPRODUCT((B$5:B$16=$A27)*Z$5:Z$16*$F$5:$F$16)+SUMPRODUCT((C$5:C$16=$A27)*AA$5:AA$16*$F$5:$F$16)+SUMPRODUCT((D$5:D$16=$A27)*AB$5:AB$16*$F$5:$F$16)+SUMPRODUCT((E$5:E$16=$A27)*AC$5:AC$16*$F$5:$F$16) -> 7470 | G27: =F27-B27 -> -1030 | H27: =F27/$F$29 -> 0.13557169
A28: Email/WhatsApp | B28: =SUMPRODUCT((B$5:B$16=$A28)*J$5:J$16*$F$5:$F$16)+SUMPRODUCT((C$5:C$16=$A28)*K$5:K$16*$F$5:$F$16)+SUMPRODUCT((D$5:D$16=$A28)*L$5:L$16*$F$5:$F$16)+SUMPRODUCT((E$5:E$16=$A28)*M$5:M$16*$F$5:$F$16) -> 15300 | C28: =SUMPRODUCT((B$5:B$16=$A28)*N$5:N$16*$F$5:$F$16)+SUMPRODUCT((C$5:C$16=$A28)*O$5:O$16*$F$5:$F$16)+SUMPRODUCT((D$5:D$16=$A28)*P$5:P$16*$F$5:$F$16)+SUMPRODUCT((E$5:E$16=$A28)*Q$5:Q$16*$F$5:$F$16) -> 4600 | D28: =SUMPRODUCT((B$5:B$16=$A28)*R$5:R$16*$F$5:$F$16)+SUMPRODUCT((C$5:C$16=$A28)*S$5:S$16*$F$5:$F$16)+SUMPRODUCT((D$5:D$16=$A28)*T$5:T$16*$F$5:$F$16)+SUMPRODUCT((E$5:E$16=$A28)*U$5:U$16*$F$5:$F$16) -> 8166.6667 | E28: =SUMPRODUCT((B$5:B$16=$A28)*V$5:V$16*$F$5:$F$16)+SUMPRODUCT((C$5:C$16=$A28)*W$5:W$16*$F$5:$F$16)+SUMPRODUCT((D$5:D$16=$A28)*X$5:X$16*$F$5:$F$16)+SUMPRODUCT((E$5:E$16=$A28)*Y$5:Y$16*$F$5:$F$16) -> 10714.286 | F28: =SUMPRODUCT((B$5:B$16=$A28)*Z$5:Z$16*$F$5:$F$16)+SUMPRODUCT((C$5:C$16=$A28)*AA$5:AA$16*$F$5:$F$16)+SUMPRODUCT((D$5:D$16=$A28)*AB$5:AB$16*$F$5:$F$16)+SUMPRODUCT((E$5:E$16=$A28)*AC$5:AC$16*$F$5:$F$16) -> 8880 | G28: =F28-B28 -> -6420 | H28: =F28/$F$29 -> 0.16116152
A29: Total (must equal path revenue) | B29: =SUM(B21:B28) -> 55100 | C29: =SUM(C21:C28) -> 55100 | D29: =SUM(D21:D28) -> 55100 | E29: =SUM(E21:E28) -> 55100 | F29: =SUM(F21:F28) -> 55100 | H29: =SUM(H21:H28) -> 1
A31: What this tells us
A32: ="TikTok: "&TEXT(B21,"#,##0")&" EGP on last click vs "&TEXT(F21,"#,##0")&" EGP position-based. It opens the most journeys, so cutting it on last-click ROAS would starve Search and Retargeting." -> TikTok: 0 EGP on last click vs 10,780 EGP position-based. It opens the most journeys, so cutting it on last-click ROAS would starve Search and Retargeting.
A33: ="Google Search: "&TEXT(B26,"#,##0")&" EGP on last click vs "&TEXT(F26,"#,##0")&" EGP position-based. It closes demand other channels create; last click over-credits it." -> Google Search: 23,400 EGP on last click vs 13,220 EGP position-based. It closes demand other channels create; last click over-credits it.
A34: ="YouTube + Snapchat together hold only "&TEXT(H22+H23,"0.0%")&" of position-based credit: weak as openers and as closers." -> YouTube + Snapchat together hold only 7.1% of position-based credit: weak as openers and as closers.
A35: ="Why position-based and not GA4 data-driven: data-driven needs about 600 conversions a month. The test month closed about 220, so a rule-based model that credits both opener and closer is the honest stand-in." -> Why position-based and not GA4 data-driven: data-driven needs about 600 conversions a month. The test month closed about 220, so a rule-based model that credits both opener and closer is the honest stand-in.
A36: ="Decision rule used in the Dashboard: upper-funnel lines below break-even ROAS stay only if their position-based share clears the assist threshold on the Inputs sheet." -> Decision rule used in the Dashboard: upper-funnel lines below break-even ROAS stay only if their position-based share clears the assist threshold on the Inputs sheet.

Sheet Sample Data
A1: Simulated Test Month · daily platform export (Nov 2026)
A2: SIMULATED DATA for the case study, generated from the Media Plan benchmarks with realistic noise and built-in patterns. Not IKEA Egypt actuals.
A4: Date | B4: Day | C4: Week | D4: ID | E4: Platform | F4: Stage | G4: Spend (EGP) | H4: Impressions | I4: Clicks | J4: Add to cart | K4: Purchases | L4: Revenue (EGP) | M4: CTR | N4: CPC | O4: CPM | P4: CVR | Q4: CPA | R4: ROAS
A5: 46327 | B5: 1 | C5: =MIN(4,INT((B5-1)/7)+1) -> 1 | D5: C01 | E5: =INDEX('Media Plan'!$B$5:$B$12,MATCH(D5,'Media Plan'!$A$5:$A$12,0)) -> TikTok | F5: =INDEX('Media Plan'!$D$5:$D$12,MATCH(D5,'Media Plan'!$A$5:$A$12,0)) -> TOFU | G5: 1292 | H5: 46608 | I5: 265 | J5: 2 | K5: 0 | L5: 0 | M5: =IFERROR(I5/H5,0) -> 0.0056857192 | N5: =IFERROR(G5/I5,0) -> 4.8754717 | O5: =IFERROR(G5/H5*1000,0) -> 27.720563 | P5: =IFERROR(K5/I5,0) -> 0 | Q5: =IFERROR(G5/K5,"-") -> - | R5: =IFERROR(L5/G5,0) -> 0
A6: 46327 | B6: 1 | C6: =MIN(4,INT((B6-1)/7)+1) -> 1 | D6: C02 | E6: =INDEX('Media Plan'!$B$5:$B$12,MATCH(D6,'Media Plan'!$A$5:$A$12,0)) -> YouTube | F6: =INDEX('Media Plan'!$D$5:$D$12,MATCH(D6,'Media Plan'!$A$5:$A$12,0)) -> TOFU | G6: 434 | H6: 8642 | I6: 21 | J6: 0 | K6: 0 | L6: 0 | M6: =IFERROR(I6/H6,0) -> 0.0024299931 | N6: =IFERROR(G6/I6,0) -> 20.666667 | O6: =IFERROR(G6/H6*1000,0) -> 50.219857 | P6: =IFERROR(K6/I6,0) -> 0 | Q6: =IFERROR(G6/K6,"-") -> - | R6: =IFERROR(L6/G6,0) -> 0
A7: 46327 | B7: 1 | C7: =MIN(4,INT((B7-1)/7)+1) -> 1 | D7: C03 | E7: =INDEX('Media Plan'!$B$5:$B$12,MATCH(D7,'Media Plan'!$A$5:$A$12,0)) -> Snapchat | F7: =INDEX('Media Plan'!$D$5:$D$12,MATCH(D7,'Media Plan'!$A$5:$A$12,0)) -> MOFU | G7: 389 | H7: 15546 | I7: 72 | J7: 0 | K7: 0 | L7: 0 | M7: =IFERROR(I7/H7,0) -> 0.0046314164 | N7: =IFERROR(G7/I7,0) -> 5.4027778 | O7: =IFERROR(G7/H7*1000,0) -> 25.022514 | P7: =IFERROR(K7/I7,0) -> 0 | Q7: =IFERROR(G7/K7,"-") -> - | R7: =IFERROR(L7/G7,0) -> 0
A8: 46327 | B8: 1 | C8: =MIN(4,INT((B8-1)/7)+1) -> 1 | D8: C04 | E8: =INDEX('Media Plan'!$B$5:$B$12,MATCH(D8,'Media Plan'!$A$5:$A$12,0)) -> Meta | F8: =INDEX('Media Plan'!$D$5:$D$12,MATCH(D8,'Media Plan'!$A$5:$A$12,0)) -> MOFU | G8: 1685 | H8: 32070 | I8: 450 | J8: 9 | K8: 1 | L8: 5170 | M8: =IFERROR(I8/H8,0) -> 0.014031805 | N8: =IFERROR(G8/I8,0) -> 3.7444444 | O8: =IFERROR(G8/H8*1000,0) -> 52.541316 | P8: =IFERROR(K8/I8,0) -> 0.0022222222 | Q8: =IFERROR(G8/K8,"-") -> 1685 | R8: =IFERROR(L8/G8,0) -> 3.0682493
A9: 46327 | B9: 1 | C9: =MIN(4,INT((B9-1)/7)+1) -> 1 | D9: C05 | E9: =INDEX('Media Plan'!$B$5:$B$12,MATCH(D9,'Media Plan'!$A$5:$A$12,0)) -> Google Search | F9: =INDEX('Media Plan'!$D$5:$D$12,MATCH(D9,'Media Plan'!$A$5:$A$12,0)) -> BOFU | G9: 1778 | H9: 5068 | I9: 293 | J9: 14 | K9: 2 | L9: 10470 | M9: =IFERROR(I9/H9,0) -> 0.057813733 | N9: =IFERROR(G9/I9,0) -> 6.0682594 | O9: =IFERROR(G9/H9*1000,0) -> 350.82873 | P9: =IFERROR(K9/I9,0) -> 0.0068259386 | Q9: =IFERROR(G9/K9,"-") -> 889 | R9: =IFERROR(L9/G9,0) -> 5.8886389
A10: 46327 | B10: 1 | C10: =MIN(4,INT((B10-1)/7)+1) -> 1 | D10: C06 | E10: =INDEX('Media Plan'!$B$5:$B$12,MATCH(D10,'Media Plan'!$A$5:$A$12,0)) -> Google PMax | F10: =INDEX('Media Plan'!$D$5:$D$12,MATCH(D10,'Media Plan'!$A$5:$A$12,0)) -> BOFU | G10: 1163 | H10: 16025 | I10: 242 | J10: 7 | K10: 2 | L10: 10530 | M10: =IFERROR(I10/H10,0) -> 0.015101404 | N10: =IFERROR(G10/I10,0) -> 4.8057851 | O10: =IFERROR(G10/H10*1000,0) -> 72.574103 | P10: =IFERROR(K10/I10,0) -> 0.0082644628 | Q10: =IFERROR(G10/K10,"-") -> 581.5 | R10: =IFERROR(L10/G10,0) -> 9.0541702
A11: 46327 | B11: 1 | C11: =MIN(4,INT((B11-1)/7)+1) -> 1 | D11: C07 | E11: =INDEX('Media Plan'!$B$5:$B$12,MATCH(D11,'Media Plan'!$A$5:$A$12,0)) -> Meta | F11: =INDEX('Media Plan'!$D$5:$D$12,MATCH(D11,'Media Plan'!$A$5:$A$12,0)) -> BOFU | G11: 1273 | H11: 15255 | I11: 245 | J11: 9 | K11: 1 | L11: 4120 | M11: =IFERROR(I11/H11,0) -> 0.016060308 | N11: =IFERROR(G11/I11,0) -> 5.1959184 | O11: =IFERROR(G11/H11*1000,0) -> 83.44805 | P11: =IFERROR(K11/I11,0) -> 0.0040816327 | Q11: =IFERROR(G11/K11,"-") -> 1273 | R11: =IFERROR(L11/G11,0) -> 3.2364493
A12: 46327 | B12: 1 | C12: =MIN(4,INT((B12-1)/7)+1) -> 1 | D12: C08 | E12: =INDEX('Media Plan'!$B$5:$B$12,MATCH(D12,'Media Plan'!$A$5:$A$12,0)) -> Email + WhatsApp | F12: =INDEX('Media Plan'!$D$5:$D$12,MATCH(D12,'Media Plan'!$A$5:$A$12,0)) -> CARE | G12: 377 | H12: 651 | I12: 54 | J12: 6 | K12: 1 | L12: 4200 | M12: =IFERROR(I12/H12,0) -> 0.082949309 | N12: =IFERROR(G12/I12,0) -> 6.9814815 | O12: =IFERROR(G12/H12*1000,0) -> 579.10906 | P12: =IFERROR(K12/I12,0) -> 0.018518519 | Q12: =IFERROR(G12/K12,"-") -> 377 | R12: =IFERROR(L12/G12,0) -> 11.140584
A13: 46328 | B13: 2 | C13: =MIN(4,INT((B13-1)/7)+1) -> 1 | D13: C01 | E13: =INDEX('Media Plan'!$B$5:$B$12,MATCH(D13,'Media Plan'!$A$5:$A$12,0)) -> TikTok | F13: =INDEX('Media Plan'!$D$5:$D$12,MATCH(D13,'Media Plan'!$A$5:$A$12,0)) -> TOFU | G13: 1381 | H13: 44968 | I13: 277 | J13: 2 | K13: 0 | L13: 0 | M13: =IFERROR(I13/H13,0) -> 0.006159936 | N13: =IFERROR(G13/I13,0) -> 4.9855596 | O13: =IFERROR(G13/H13*1000,0) -> 30.710728 | P13: =IFERROR(K13/I13,0) -> 0 | Q13: =IFERROR(G13/K13,"-") -> - | R13: =IFERROR(L13/G13,0) -> 0
A14: 46328 | B14: 2 | C14: =MIN(4,INT((B14-1)/7)+1) -> 1 | D14: C02 | E14: =INDEX('Media Plan'!$B$5:$B$12,MATCH(D14,'Media Plan'!$A$5:$A$12,0)) -> YouTube | F14: =INDEX('Media Plan'!$D$5:$D$12,MATCH(D14,'Media Plan'!$A$5:$A$12,0)) -> TOFU | G14: 383 | H14: 8265 | I14: 25 | J14: 0 | K14: 0 | L14: 0 | M14: =IFERROR(I14/H14,0) -> 0.0030248034 | N14: =IFERROR(G14/I14,0) -> 15.32 | O14: =IFERROR(G14/H14*1000,0) -> 46.339988 | P14: =IFERROR(K14/I14,0) -> 0 | Q14: =IFERROR(G14/K14,"-") -> - | R14: =IFERROR(L14/G14,0) -> 0
A15: 46328 | B15: 2 | C15: =MIN(4,INT((B15-1)/7)+1) -> 1 | D15: C03 | E15: =INDEX('Media Plan'!$B$5:$B$12,MATCH(D15,'Media Plan'!$A$5:$A$12,0)) -> Snapchat | F15: =INDEX('Media Plan'!$D$5:$D$12,MATCH(D15,'Media Plan'!$A$5:$A$12,0)) -> MOFU | G15: 435 | H15: 16495 | I15: 92 | J15: 0 | K15: 0 | L15: 0 | M15: =IFERROR(I15/H15,0) -> 0.0055774477 | N15: =IFERROR(G15/I15,0) -> 4.7282609 | O15: =IFERROR(G15/H15*1000,0) -> 26.371628 | P15: =IFERROR(K15/I15,0) -> 0 | Q15: =IFERROR(G15/K15,"-") -> - | R15: =IFERROR(L15/G15,0) -> 0
A16: 46328 | B16: 2 | C16: =MIN(4,INT((B16-1)/7)+1) -> 1 | D16: C04 | E16: =INDEX('Media Plan'!$B$5:$B$12,MATCH(D16,'Media Plan'!$A$5:$A$12,0)) -> Meta | F16: =INDEX('Media Plan'!$D$5:$D$12,MATCH(D16,'Media Plan'!$A$5:$A$12,0)) -> MOFU | G16: 1593 | H16: 30081 | I16: 385 | J16: 8 | K16: 2 | L16: 10150 | M16: =IFERROR(I16/H16,0) -> 0.012798777 | N16: =IFERROR(G16/I16,0) -> 4.1376623 | O16: =IFERROR(G16/H16*1000,0) -> 52.957016 | P16: =IFERROR(K16/I16,0) -> 0.0051948052 | Q16: =IFERROR(G16/K16,"-") -> 796.5 | R16: =IFERROR(L16/G16,0) -> 6.3716259
... A244: 46356 | B244: 30 | C244: =MIN(4,INT((B244-1)/7)+1) -> 4 | D244: C08 | E244: =INDEX('Media Plan'!$B$5:$B$12,MATCH(D244,'Media Plan'!$A$5:$A$12,0)) -> Email + WhatsApp | F244: =INDEX('Media Plan'!$D$5:$D$12,MATCH(D244,'Media Plan'!$A$5:$A$12,0)) -> CARE | G244: 384 | H244: 597 | I244: 44 | J244: 6 | K244: 2 | L244: 10330 | M244: =IFERROR(I244/H244,0) -> 0.073701843 | N244: =IFERROR(G244/I244,0) -> 8.7272727 | O244: =IFERROR(G244/H244*1000,0) -> 643.21608 | P244: =IFERROR(K244/I244,0) -> 0.045454545 | Q244: =IFERROR(G244/K244,"-") -> 192 | R244: =IFERROR(L244/G244,0) -> 26.901042

Sheet Dashboard
A1: Performance Dashboard · simulated test month
A2: Every number is a SUMIFS on the Sample Data sheet. Status is decided by the rules on the Inputs sheet.
A4: Spend (EGP) | B4: Revenue (EGP) | C4: Purchases | D4: Blended ROAS | E4: Blended CPA (EGP) | F4: Contribution after ads (EGP) | G4: Target ROAS
A5: =SUM('Sample Data'!$G$5:$G$244) -> 249997 | B5: =SUM('Sample Data'!$L$5:$L$244) -> 1027510 | C5: =SUM('Sample Data'!$K$5:$K$244) -> 219 | D5: =IFERROR(B5/A5,0) -> 4.1100893 | E5: =IFERROR(A5/C5,0) -> 1141.5388 | F5: =B5*Inputs!$B$8-A5 -> 109631.5 | G5: =Inputs!$B$10 -> 3.5
A7: Campaign scorecard
A8: ID | B8: Platform | C8: Stage | D8: Planned (EGP) | E8: Spend (EGP) | F8: Pacing | G8: Impressions | H8: Clicks | I8: Purchases | J8: Revenue (EGP) | K8: CTR | L8: CPC | M8: CVR | N8: CPA | O8: ROAS | P8: vs target | Q8: Assist share (pos.-based) | R8: CTR W1 | S8: CTR W4 | T8: CTR change | U8: Fatigue | V8: Status
A9: ='Media Plan'!A5 -> C01 | B9: ='Media Plan'!B5 -> TikTok | C9: ='Media Plan'!D5 -> TOFU | D9: ='Media Plan'!J5 -> 37500 | E9: =SUMIFS('Sample Data'!$G$5:$G$244,'Sample Data'!$D$5:$D$244,$A9) -> 38529 | F9: =IFERROR(E9/D9,0) -> 1.02744 | G9: =SUMIFS('Sample Data'!$H$5:$H$244,'Sample Data'!$D$5:$D$244,$A9) -> 1286300 | H9: =SUMIFS('Sample Data'!$I$5:$I$244,'Sample Data'!$D$5:$D$244,$A9) -> 7810 | I9: =SUMIFS('Sample Data'!$K$5:$K$244,'Sample Data'!$D$5:$D$244,$A9) -> 3 | J9: =SUMIFS('Sample Data'!$L$5:$L$244,'Sample Data'!$D$5:$D$244,$A9) -> 14040 | K9: =IFERROR(H9/G9,0) -> 0.0060716785 | L9: =IFERROR(E9/H9,0) -> 4.9332907 | M9: =IFERROR(I9/H9,0) -> 0.00038412292 | N9: =IFERROR(E9/I9,"-") -> 12843 | O9: =IFERROR(J9/E9,0) -> 0.36440084 | P9: =IFERROR(O9/Inputs!$B$10-1,0) -> -0.89588547 | Q9: =IFERROR(INDEX(Attribution!$H$21:$H$28,MATCH('Media Plan'!C5,Attribution!$A$21:$A$28,0)),0) -> 0.19564428 | R9: =IFERROR(SUMIFS('Sample Data'!$I$5:$I$244,'Sample Data'!$D$5:$D$244,$A9,'Sample Data'!$C$5:$C$244,1)/SUMIFS('Sample Data'!$H$5:$H$244,'Sample Data'!$D$5:$D$244,$A9,'Sample Data'!$C$5:$C$244,1),0) -> 0.0059070443 | S9: =IFERROR(SUMIFS('Sample Data'!$I$5:$I$244,'Sample Data'!$D$5:$D$244,$A9,'Sample Data'!$C$5:$C$244,4)/SUMIFS('Sample Data'!$H$5:$H$244,'Sample Data'!$D$5:$D$244,$A9,'Sample Data'!$C$5:$C$244,4),0) -> 0.005936585 | T9: =IFERROR(S9/R9-1,0) -> 0.0050009232 | U9: =IF(T9<=-Inputs!$B$14,"FATIGUE","") | V9: =IF(O9>=Inputs!$B$10*Inputs!$B$12,"SCALE",IF(O9>=Inputs!$B$9,"HOLD",IF(OR(C9="TOFU",C9="MOFU"),IF(Q9>=Inputs!$B$13,"KEEP: ASSISTS","CUT"),"FIX")))&IF(U9="FATIGUE"," + REFRESH CREATIVE","") -> KEEP: ASSISTS
A10: ='Media Plan'!A6 -> C02 | B10: ='Media Plan'!B6 -> YouTube | C10: ='Media Plan'!D6 -> TOFU | D10: ='Media Plan'!J6 -> 12500 | E10: =SUMIFS('Sample Data'!$G$5:$G$244,'Sample Data'!$D$5:$D$244,$A10) -> 12648 | F10: =IFERROR(E10/D10,0) -> 1.01184 | G10: =SUMIFS('Sample Data'!$H$5:$H$244,'Sample Data'!$D$5:$D$244,$A10) -> 266686 | H10: =SUMIFS('Sample Data'!$I$5:$I$244,'Sample Data'!$D$5:$D$244,$A10) -> 724 | I10: =SUMIFS('Sample Data'!$K$5:$K$244,'Sample Data'!$D$5:$D$244,$A10) -> 2 | J10: =SUMIFS('Sample Data'!$L$5:$L$244,'Sample Data'!$D$5:$D$244,$A10) -> 11170 | K10: =IFERROR(H10/G10,0) -> 0.0027148032 | L10: =IFERROR(E10/H10,0) -> 17.469613 | M10: =IFERROR(I10/H10,0) -> 0.0027624309 | N10: =IFERROR(E10/I10,"-") -> 6324 | O10: =IFERROR(J10/E10,0) -> 0.88314358 | P10: =IFERROR(O10/Inputs!$B$10-1,0) -> -0.74767326 | Q10: =IFERROR(INDEX(Attribution!$H$21:$H$28,MATCH('Media Plan'!C6,Attribution!$A$21:$A$28,0)),0) -> 0.037205082 | R10: =IFERROR(SUMIFS('Sample Data'!$I$5:$I$244,'Sample Data'!$D$5:$D$244,$A10,'Sample Data'!$C$5:$C$244,1)/SUMIFS('Sample Data'!$H$5:$H$244,'Sample Data'!$D$5:$D$244,$A10,'Sample Data'!$C$5:$C$244,1),0) -> 0.0028888703 | S10: =IFERROR(SUMIFS('Sample Data'!$I$5:$I$244,'Sample Data'!$D$5:$D$244,$A10,'Sample Data'!$C$5:$C$244,4)/SUMIFS('Sample Data'!$H$5:$H$244,'Sample Data'!$D$5:$D$244,$A10,'Sample Data'!$C$5:$C$244,4),0) -> 0.0026034276 | T10: =IFERROR(S10/R10-1,0) -> -0.098807721 | U10: =IF(T10<=-Inputs!$B$14,"FATIGUE","") | V10: =IF(O10>=Inputs!$B$10*Inputs!$B$12,"SCALE",IF(O10>=Inputs!$B$9,"HOLD",IF(OR(C10="TOFU",C10="MOFU"),IF(Q10>=Inputs!$B$13,"KEEP: ASSISTS","CUT"),"FIX")))&IF(U10="FATIGUE"," + REFRESH CREATIVE","") -> CUT
A11: ='Media Plan'!A7 -> C03 | B11: ='Media Plan'!B7 -> Snapchat | C11: ='Media Plan'!D7 -> MOFU | D11: ='Media Plan'!J7 -> 12500 | E11: =SUMIFS('Sample Data'!$G$5:$G$244,'Sample Data'!$D$5:$D$244,$A11) -> 12374 | F11: =IFERROR(E11/D11,0) -> 0.98992 | G11: =SUMIFS('Sample Data'!$H$5:$H$244,'Sample Data'!$D$5:$D$244,$A11) -> 492271 | H11: =SUMIFS('Sample Data'!$I$5:$I$244,'Sample Data'!$D$5:$D$244,$A11) -> 2600 | I11: =SUMIFS('Sample Data'!$K$5:$K$244,'Sample Data'!$D$5:$D$244,$A11) -> 2 | J11: =SUMIFS('Sample Data'!$L$5:$L$244,'Sample Data'!$D$5:$D$244,$A11) -> 8990 | K11: =IFERROR(H11/G11,0) -> 0.0052816436 | L11: =IFERROR(E11/H11,0) -> 4.7592308 | M11: =IFERROR(I11/H11,0) -> 0.00076923077 | N11: =IFERROR(E11/I11,"-") -> 6187 | O11: =IFERROR(J11/E11,0) -> 0.72652336 | P11: =IFERROR(O11/Inputs!$B$10-1,0) -> -0.7924219 | Q11: =IFERROR(INDEX(Attribution!$H$21:$H$28,MATCH('Media Plan'!C7,Attribution!$A$21:$A$28,0)),0) -> 0.033575318 | R11: =IFERROR(SUMIFS('Sample Data'!$I$5:$I$244,'Sample Data'!$D$5:$D$244,$A11,'Sample Data'!$C$5:$C$244,1)/SUMIFS('Sample Data'!$H$5:$H$244,'Sample Data'!$D$5:$D$244,$A11,'Sample Data'!$C$5:$C$244,1),0) -> 0.0053483959 | S11: =IFERROR(SUMIFS('Sample Data'!$I$5:$I$244,'Sample Data'!$D$5:$D$244,$A11,'Sample Data'!$C$5:$C$244,4)/SUMIFS('Sample Data'!$H$5:$H$244,'Sample Data'!$D$5:$D$244,$A11,'Sample Data'!$C$5:$C$244,4),0) -> 0.0053584243 | T11: =IFERROR(S11/R11-1,0) -> 0.001875018 | U11: =IF(T11<=-Inputs!$B$14,"FATIGUE","") | V11: =IF(O11>=Inputs!$B$10*Inputs!$B$12,"SCALE",IF(O11>=Inputs!$B$9,"HOLD",IF(OR(C11="TOFU",C11="MOFU"),IF(Q11>=Inputs!$B$13,"KEEP: ASSISTS","CUT"),"FIX")))&IF(U11="FATIGUE"," + REFRESH CREATIVE","") -> CUT
A12: ='Media Plan'!A8 -> C04 | B12: ='Media Plan'!B8 -> Meta | C12: ='Media Plan'!D8 -> MOFU | D12: ='Media Plan'!J8 -> 50000 | E12: =SUMIFS('Sample Data'!$G$5:$G$244,'Sample Data'!$D$5:$D$244,$A12) -> 49719 | F12: =IFERROR(E12/D12,0) -> 0.99438 | G12: =SUMIFS('Sample Data'!$H$5:$H$244,'Sample Data'!$D$5:$D$244,$A12) -> 842473 | H12: =SUMIFS('Sample Data'!$I$5:$I$244,'Sample Data'!$D$5:$D$244,$A12) -> 10117 | I12: =SUMIFS('Sample Data'!$K$5:$K$244,'Sample Data'!$D$5:$D$244,$A12) -> 33 | J12: =SUMIFS('Sample Data'!$L$5:$L$244,'Sample Data'!$D$5:$D$244,$A12) -> 156240 | K12: =IFERROR(H12/G12,0) -> 0.012008693 | L12: =IFERROR(E12/H12,0) -> 4.9144015 | M12: =IFERROR(I12/H12,0) -> 0.0032618365 | N12: =IFERROR(E12/I12,"-") -> 1506.6364 | O12: =IFERROR(J12/E12,0) -> 3.1424606 | P12: =IFERROR(O12/Inputs!$B$10-1,0) -> -0.10215411 | Q12: =IFERROR(INDEX(Attribution!$H$21:$H$28,MATCH('Media Plan'!C8,Attribution!$A$21:$A$28,0)),0) -> 0.097640653 | R12: =IFERROR(SUMIFS('Sample Data'!$I$5:$I$244,'Sample Data'!$D$5:$D$244,$A12,'Sample Data'!$C$5:$C$244,1)/SUMIFS('Sample Data'!$H$5:$H$244,'Sample Data'!$D$5:$D$244,$A12,'Sample Data'!$C$5:$C$244,1),0) -> 0.013468922 | S12: =IFERROR(SUMIFS('Sample Data'!$I$5:$I$244,'Sample Data'!$D$5:$D$244,$A12,'Sample Data'!$C$5:$C$244,4)/SUMIFS('Sample Data'!$H$5:$H$244,'Sample Data'!$D$5:$D$244,$A12,'Sample Data'!$C$5:$C$244,4),0) -> 0.0089033831 | T12: =IFERROR(S12/R12-1,0) -> -0.33896841 | U12: =IF(T12<=-Inputs!$B$14,"FATIGUE","") -> FATIGUE | V12: =IF(O12>=Inputs!$B$10*Inputs!$B$12,"SCALE",IF(O12>=Inputs!$B$9,"HOLD",IF(OR(C12="TOFU",C12="MOFU"),IF(Q12>=Inputs!$B$13,"KEEP: ASSISTS","CUT"),"FIX")))&IF(U12="FATIGUE"," + REFRESH CREATIVE","") -> HOLD + REFRESH CREATIVE
A13: ='Media Plan'!A9 -> C05 | B13: ='Media Plan'!B9 -> Google Search | C13: ='Media Plan'!D9 -> BOFU | D13: ='Media Plan'!J9 -> 55000 | E13: =SUMIFS('Sample Data'!$G$5:$G$244,'Sample Data'!$D$5:$D$244,$A13) -> 53340 | F13: =IFERROR(E13/D13,0) -> 0.96981818 | G13: =SUMIFS('Sample Data'!$H$5:$H$244,'Sample Data'!$D$5:$D$244,$A13) -> 148147 | H13: =SUMIFS('Sample Data'!$I$5:$I$244,'Sample Data'!$D$5:$D$244,$A13) -> 9334 | I13: =SUMIFS('Sample Data'!$K$5:$K$244,'Sample Data'!$D$5:$D$244,$A13) -> 82 | J13: =SUMIFS('Sample Data'!$L$5:$L$244,'Sample Data'!$D$5:$D$244,$A13) -> 387450 | K13: =IFERROR(H13/G13,0) -> 0.063004988 | L13: =IFERROR(E13/H13,0) -> 5.7145918 | M13: =IFERROR(I13/H13,0) -> 0.0087850868 | N13: =IFERROR(E13/I13,"-") -> 650.4878 | O13: =IFERROR(J13/E13,0) -> 7.2637795 | P13: =IFERROR(O13/Inputs!$B$10-1,0) -> 1.0753656 | Q13: =IFERROR(INDEX(Attribution!$H$21:$H$28,MATCH('Media Plan'!C9,Attribution!$A$21:$A$28,0)),0) -> 0.2399274 | R13: =IFERROR(SUMIFS('Sample Data'!$I$5:$I$244,'Sample Data'!$D$5:$D$244,$A13,'Sample Data'!$C$5:$C$244,1)/SUMIFS('Sample Data'!$H$5:$H$244,'Sample Data'!$D$5:$D$244,$A13,'Sample Data'!$C$5:$C$244,1),0) -> 0.064031667 | S13: =IFERROR(SUMIFS('Sample Data'!$I$5:$I$244,'Sample Data'!$D$5:$D$244,$A13,'Sample Data'!$C$5:$C$244,4)/SUMIFS('Sample Data'!$H$5:$H$244,'Sample Data'!$D$5:$D$244,$A13,'Sample Data'!$C$5:$C$244,4),0) -> 0.06326238 | T13: =IFERROR(S13/R13-1,0) -> -0.012014157 | U13: =IF(T13<=-Inputs!$B$14,"FATIGUE","") | V13: =IF(O13>=Inputs!$B$10*Inputs!$B$12,"SCALE",IF(O13>=Inputs!$B$9,"HOLD",IF(OR(C13="TOFU",C13="MOFU"),IF(Q13>=Inputs!$B$13,"KEEP: ASSISTS","CUT"),"FIX")))&IF(U13="FATIGUE"," + REFRESH CREATIVE","") -> SCALE
A14: ='Media Plan'!A10 -> C06 | B14: ='Media Plan'!B10 -> Google PMax | C14: ='Media Plan'!D10 -> BOFU | D14: ='Media Plan'!J10 -> 32500 | E14: =SUMIFS('Sample Data'!$G$5:$G$244,'Sample Data'!$D$5:$D$244,$A14) -> 32705 | F14: =IFERROR(E14/D14,0) -> 1.0063077 | G14: =SUMIFS('Sample Data'!$H$5:$H$244,'Sample Data'!$D$5:$D$244,$A14) -> 466390 | H14: =SUMIFS('Sample Data'!$I$5:$I$244,'Sample Data'!$D$5:$D$244,$A14) -> 6974 | I14: =SUMIFS('Sample Data'!$K$5:$K$244,'Sample Data'!$D$5:$D$244,$A14) -> 28 | J14: =SUMIFS('Sample Data'!$L$5:$L$244,'Sample Data'!$D$5:$D$244,$A14) -> 132370 | K14: =IFERROR(H14/G14,0) -> 0.014953151 | L14: =IFERROR(E14/H14,0) -> 4.6895612 | M14: =IFERROR(I14/H14,0) -> 0.0040149125 | N14: =IFERROR(E14/I14,"-") -> 1168.0357 | O14: =IFERROR(J14/E14,0) -> 4.0473934 | P14: =IFERROR(O14/Inputs!$B$10-1,0) -> 0.1563981 | Q14: =IFERROR(INDEX(Attribution!$H$21:$H$28,MATCH('Media Plan'!C10,Attribution!$A$21:$A$28,0)),0) -> 0.13557169 | R14: =IFERROR(SUMIFS('Sample Data'!$I$5:$I$244,'Sample Data'!$D$5:$D$244,$A14,'Sample Data'!$C$5:$C$244,1)/SUMIFS('Sample Data'!$H$5:$H$244,'Sample Data'!$D$5:$D$244,$A14,'Sample Data'!$C$5:$C$244,1),0) -> 0.014619559 | S14: =IFERROR(SUMIFS('Sample Data'!$I$5:$I$244,'Sample Data'!$D$5:$D$244,$A14,'Sample Data'!$C$5:$C$244,4)/SUMIFS('Sample Data'!$H$5:$H$244,'Sample Data'!$D$5:$D$244,$A14,'Sample Data'!$C$5:$C$244,4),0) -> 0.014695348 | T14: =IFERROR(S14/R14-1,0) -> 0.0051840882 | U14: =IF(T14<=-Inputs!$B$14,"FATIGUE","") | V14: =IF(O14>=Inputs!$B$10*Inputs!$B$12,"SCALE",IF(O14>=Inputs!$B$9,"HOLD",IF(OR(C14="TOFU",C14="MOFU"),IF(Q14>=Inputs!$B$13,"KEEP: ASSISTS","CUT"),"FIX")))&IF(U14="FATIGUE"," + REFRESH CREATIVE","") -> HOLD
A15: ='Media Plan'!A11 -> C07 | B15: ='Media Plan'!B11 -> Meta | C15: ='Media Plan'!D11 -> BOFU | D15: ='Media Plan'!J11 -> 37500 | E15: =SUMIFS('Sample Data'!$G$5:$G$244,'Sample Data'!$D$5:$D$244,$A15) -> 37984 | F15: =IFERROR(E15/D15,0) -> 1.0129067 | G15: =SUMIFS('Sample Data'!$H$5:$H$244,'Sample Data'!$D$5:$D$244,$A15) -> 412727 | H15: =SUMIFS('Sample Data'!$I$5:$I$244,'Sample Data'!$D$5:$D$244,$A15) -> 7028 | I15: =SUMIFS('Sample Data'!$K$5:$K$244,'Sample Data'!$D$5:$D$244,$A15) -> 43 | J15: =SUMIFS('Sample Data'!$L$5:$L$244,'Sample Data'!$D$5:$D$244,$A15) -> 200860 | K15: =IFERROR(H15/G15,0) -> 0.017028205 | L15: =IFERROR(E15/H15,0) -> 5.404667 | M15: =IFERROR(I15/H15,0) -> 0.0061183836 | N15: =IFERROR(E15/I15,"-") -> 883.34884 | O15: =IFERROR(J15/E15,0) -> 5.288016 | P15: =IFERROR(O15/Inputs!$B$10-1,0) -> 0.51086172 | Q15: =IFERROR(INDEX(Attribution!$H$21:$H$28,MATCH('Media Plan'!C11,Attribution!$A$21:$A$28,0)),0) -> 0.099274047 | R15: =IFERROR(SUMIFS('Sample Data'!$I$5:$I$244,'Sample Data'!$D$5:$D$244,$A15,'Sample Data'!$C$5:$C$244,1)/SUMIFS('Sample Data'!$H$5:$H$244,'Sample Data'!$D$5:$D$244,$A15,'Sample Data'!$C$5:$C$244,1),0) -> 0.01773416 | S15: =IFERROR(SUMIFS('Sample Data'!$I$5:$I$244,'Sample Data'!$D$5:$D$244,$A15,'Sample Data'!$C$5:$C$244,4)/SUMIFS('Sample Data'!$H$5:$H$244,'Sample Data'!$D$5:$D$244,$A15,'Sample Data'!$C$5:$C$244,4),0) -> 0.015310028 | T15: =IFERROR(S15/R15-1,0) -> -0.13669279 | U15: =IF(T15<=-Inputs!$B$14,"FATIGUE","") | V15: =IF(O15>=Inputs!$B$10*Inputs!$B$12,"SCALE",IF(O15>=Inputs!$B$9,"HOLD",IF(OR(C15="TOFU",C15="MOFU"),IF(Q15>=Inputs!$B$13,"KEEP: ASSISTS","CUT"),"FIX")))&IF(U15="FATIGUE"," + REFRESH CREATIVE","") -> SCALE
A16: ='Media Plan'!A12 -> C08 | B16: ='Media Plan'!B12 -> Email + WhatsApp | C16: ='Media Plan'!D12 -> CARE | D16: ='Media Plan'!J12 -> 12500 | E16: =SUMIFS('Sample Data'!$G$5:$G$244,'Sample Data'!$D$5:$D$244,$A16) -> 12698 | F16: =IFERROR(E16/D16,0) -> 1.01584 | G16: =SUMIFS('Sample Data'!$H$5:$H$244,'Sample Data'!$D$5:$D$244,$A16) -> 20939 | H16: =SUMIFS('Sample Data'!$I$5:$I$244,'Sample Data'!$D$5:$D$244,$A16) -> 1670 | I16: =SUMIFS('Sample Data'!$K$5:$K$244,'Sample Data'!$D$5:$D$244,$A16) -> 26 | J16: =SUMIFS('Sample Data'!$L$5:$L$244,'Sample Data'!$D$5:$D$244,$A16) -> 116390 | K16: =IFERROR(H16/G16,0) -> 0.07975548 | L16: =IFERROR(E16/H16,0) -> 7.6035928 | M16: =IFERROR(I16/H16,0) -> 0.015568862 | N16: =IFERROR(E16/I16,"-") -> 488.38462 | O16: =IFERROR(J16/E16,0) -> 9.1660104 | P16: =IFERROR(O16/Inputs!$B$10-1,0) -> 1.6188601 | Q16: =IFERROR(INDEX(Attribution!$H$21:$H$28,MATCH('Media Plan'!C12,Attribution!$A$21:$A$28,0)),0) -> 0.16116152 | R16: =IFERROR(SUMIFS('Sample Data'!$I$5:$I$244,'Sample Data'!$D$5:$D$244,$A16,'Sample Data'!$C$5:$C$244,1)/SUMIFS('Sample Data'!$H$5:$H$244,'Sample Data'!$D$5:$D$244,$A16,'Sample Data'!$C$5:$C$244,1),0) -> 0.0817288 | S16: =IFERROR(SUMIFS('Sample Data'!$I$5:$I$244,'Sample Data'!$D$5:$D$244,$A16,'Sample Data'!$C$5:$C$244,4)/SUMIFS('Sample Data'!$H$5:$H$244,'Sample Data'!$D$5:$D$244,$A16,'Sample Data'!$C$5:$C$244,4),0) -> 0.081085295 | T16: =IFERROR(S16/R16-1,0) -> -0.0078736526 | U16: =IF(T16<=-Inputs!$B$14,"FATIGUE","") | V16: =IF(O16>=Inputs!$B$10*Inputs!$B$12,"SCALE",IF(O16>=Inputs!$B$9,"HOLD",IF(OR(C16="TOFU",C16="MOFU"),IF(Q16>=Inputs!$B$13,"KEEP: ASSISTS","CUT"),"FIX")))&IF(U16="FATIGUE"," + REFRESH CREATIVE","") -> SCALE
A17: TOTAL | D17: =SUM(D9:D16) -> 250000 | E17: =SUM(E9:E16) -> 249997 | F17: =IFERROR(E17/D17,0) -> 0.999988 | G17: =SUM(G9:G16) -> 3935933 | H17: =SUM(H9:H16) -> 46257 | I17: =SUM(I9:I16) -> 219 | J17: =SUM(J9:J16) -> 1027510 | K17: =IFERROR(H17/G17,0) -> 0.011752487 | L17: =IFERROR(E17/H17,0) -> 5.4045226 | M17: =IFERROR(I17/H17,0) -> 0.0047344186 | N17: =IFERROR(E17/I17,0) -> 1141.5388 | O17: =IFERROR(J17/E17,0) -> 4.1100893 | P17: =IFERROR(O17/Inputs!$B$10-1,0) -> 0.17431123
A19: Weekly trend
A20: ID | B20: Platform | C20: CTR W1 | D20: CTR W2 | E20: CTR W3 | F20: CTR W4 | G20: CPM W1 | H20: CPM W4 | I20: ROAS W1 | J20: ROAS W2 | K20: ROAS W3 | L20: ROAS W4
A21: =A9 -> C01 | B21: =B9 -> TikTok | C21: =IFERROR(SUMIFS('Sample Data'!$I$5:$I$244,'Sample Data'!$D$5:$D$244,$A21,'Sample Data'!$C$5:$C$244,1)/SUMIFS('Sample Data'!$H$5:$H$244,'Sample Data'!$D$5:$D$244,$A21,'Sample Data'!$C$5:$C$244,1),0) -> 0.0059070443 | D21: =IFERROR(SUMIFS('Sample Data'!$I$5:$I$244,'Sample Data'!$D$5:$D$244,$A21,'Sample Data'!$C$5:$C$244,2)/SUMIFS('Sample Data'!$H$5:$H$244,'Sample Data'!$D$5:$D$244,$A21,'Sample Data'!$C$5:$C$244,2),0) -> 0.0062416794 | E21: =IFERROR(SUMIFS('Sample Data'!$I$5:$I$244,'Sample Data'!$D$5:$D$244,$A21,'Sample Data'!$C$5:$C$244,3)/SUMIFS('Sample Data'!$H$5:$H$244,'Sample Data'!$D$5:$D$244,$A21,'Sample Data'!$C$5:$C$244,3),0) -> 0.0062347731 | F21: =IFERROR(SUMIFS('Sample Data'!$I$5:$I$244,'Sample Data'!$D$5:$D$244,$A21,'Sample Data'!$C$5:$C$244,4)/SUMIFS('Sample Data'!$H$5:$H$244,'Sample Data'!$D$5:$D$244,$A21,'Sample Data'!$C$5:$C$244,4),0) -> 0.005936585 | G21: =IFERROR(SUMIFS('Sample Data'!$G$5:$G$244,'Sample Data'!$D$5:$D$244,$A21,'Sample Data'!$C$5:$C$244,1)/SUMIFS('Sample Data'!$H$5:$H$244,'Sample Data'!$D$5:$D$244,$A21,'Sample Data'!$C$5:$C$244,1)*1000,0) -> 29.804461 | H21: =IFERROR(SUMIFS('Sample Data'!$G$5:$G$244,'Sample Data'!$D$5:$D$244,$A21,'Sample Data'!$C$5:$C$244,4)/SUMIFS('Sample Data'!$H$5:$H$244,'Sample Data'!$D$5:$D$244,$A21,'Sample Data'!$C$5:$C$244,4)*1000,0) -> 30.537922 | I21: =IFERROR(SUMIFS('Sample Data'!$L$5:$L$244,'Sample Data'!$D$5:$D$244,$A21,'Sample Data'!$C$5:$C$244,1)/SUMIFS('Sample Data'!$G$5:$G$244,'Sample Data'!$D$5:$D$244,$A21,'Sample Data'!$C$5:$C$244,1),0) -> 0.50282978 | J21: =IFERROR(SUMIFS('Sample Data'!$L$5:$L$244,'Sample Data'!$D$5:$D$244,$A21,'Sample Data'!$C$5:$C$244,2)/SUMIFS('Sample Data'!$G$5:$G$244,'Sample Data'!$D$5:$D$244,$A21,'Sample Data'!$C$5:$C$244,2),0) -> 0 | K21: =IFERROR(SUMIFS('Sample Data'!$L$5:$L$244,'Sample Data'!$D$5:$D$244,$A21,'Sample Data'!$C$5:$C$244,3)/SUMIFS('Sample Data'!$G$5:$G$244,'Sample Data'!$D$5:$D$244,$A21,'Sample Data'!$C$5:$C$244,3),0) -> 0.52337285 | L21: =IFERROR(SUMIFS('Sample Data'!$L$5:$L$244,'Sample Data'!$D$5:$D$244,$A21,'Sample Data'!$C$5:$C$244,4)/SUMIFS('Sample Data'!$G$5:$G$244,'Sample Data'!$D$5:$D$244,$A21,'Sample Data'!$C$5:$C$244,4),0) -> 0.41732699
A22: =A10 -> C02 | B22: =B10 -> YouTube | C22: =IFERROR(SUMIFS('Sample Data'!$I$5:$I$244,'Sample Data'!$D$5:$D$244,$A22,'Sample Data'!$C$5:$C$244,1)/SUMIFS('Sample Data'!$H$5:$H$244,'Sample Data'!$D$5:$D$244,$A22,'Sample Data'!$C$5:$C$244,1),0) -> 0.0028888703 | D22: =IFERROR(SUMIFS('Sample Data'!$I$5:$I$244,'Sample Data'!$D$5:$D$244,$A22,'Sample Data'!$C$5:$C$244,2)/SUMIFS('Sample Data'!$H$5:$H$244,'Sample Data'!$D$5:$D$244,$A22,'Sample Data'!$C$5:$C$244,2),0) -> 0.002710423 | E22: =IFERROR(SUMIFS('Sample Data'!$I$5:$I$244,'Sample Data'!$D$5:$D$244,$A22,'Sample Data'!$C$5:$C$244,3)/SUMIFS('Sample Data'!$H$5:$H$244,'Sample Data'!$D$5:$D$244,$A22,'Sample Data'!$C$5:$C$244,3),0) -> 0.0026972248 | F22: =IFERROR(SUMIFS('Sample Data'!$I$5:$I$244,'Sample Data'!$D$5:$D$244,$A22,'Sample Data'!$C$5:$C$244,4)/SUMIFS('Sample Data'!$H$5:$H$244,'Sample Data'!$D$5:$D$244,$A22,'Sample Data'!$C$5:$C$244,4),0) -> 0.0026034276 | G22: =IFERROR(SUMIFS('Sample Data'!$G$5:$G$244,'Sample Data'!$D$5:$D$244,$A22,'Sample Data'!$C$5:$C$244,1)/SUMIFS('Sample Data'!$H$5:$H$244,'Sample Data'!$D$5:$D$244,$A22,'Sample Data'!$C$5:$C$244,1)*1000,0) -> 49.027302 | H22: =IFERROR(SUMIFS('Sample Data'!$G$5:$G$244,'Sample Data'!$D$5:$D$244,$A22,'Sample Data'!$C$5:$C$244,4)/SUMIFS('Sample Data'!$H$5:$H$244,'Sample Data'!$D$5:$D$244,$A22,'Sample Data'!$C$5:$C$244,4)*1000,0) -> 46.047355 | I22: =IFERROR(SUMIFS('Sample Data'!$L$5:$L$244,'Sample Data'!$D$5:$D$244,$A22,'Sample Data'!$C$5:$C$244,1)/SUMIFS('Sample Data'!$G$5:$G$244,'Sample Data'!$D$5:$D$244,$A22,'Sample Data'!$C$5:$C$244,1),0) -> 1.852861 | J22: =IFERROR(SUMIFS('Sample Data'!$L$5:$L$244,'Sample Data'!$D$5:$D$244,$A22,'Sample Data'!$C$5:$C$244,2)/SUMIFS('Sample Data'!$G$5:$G$244,'Sample Data'!$D$5:$D$244,$A22,'Sample Data'!$C$5:$C$244,2),0) -> 0 | K22: =IFERROR(SUMIFS('Sample Data'!$L$5:$L$244,'Sample Data'!$D$5:$D$244,$A22,'Sample Data'!$C$5:$C$244,3)/SUMIFS('Sample Data'!$G$5:$G$244,'Sample Data'!$D$5:$D$244,$A22,'Sample Data'!$C$5:$C$244,3),0) -> 0 | L22: =IFERROR(SUMIFS('Sample Data'!$L$5:$L$244,'Sample Data'!$D$5:$D$244,$A22,'Sample Data'!$C$5:$C$244,4)/SUMIFS('Sample Data'!$G$5:$G$244,'Sample Data'!$D$5:$D$244,$A22,'Sample Data'!$C$5:$C$244,4),0) -> 1.5353698
A23: =A11 -> C03 | B23: =B11 -> Snapchat | C23: =IFERROR(SUMIFS('Sample Data'!$I$5:$I$244,'Sample Data'!$D$5:$D$244,$A23,'Sample Data'!$C$5:$C$244,1)/SUMIFS('Sample Data'!$H$5:$H$244,'Sample Data'!$D$5:$D$244,$A23,'Sample Data'!$C$5:$C$244,1),0) -> 0.0053483959 | D23: =IFERROR(SUMIFS('Sample Data'!$I$5:$I$244,'Sample Data'!$D$5:$D$244,$A23,'Sample Data'!$C$5:$C$244,2)/SUMIFS('Sample Data'!$H$5:$H$244,'Sample Data'!$D$5:$D$244,$A23,'Sample Data'!$C$5:$C$244,2),0) -> 0.0051949588 | E23: =IFERROR(SUMIFS('Sample Data'!$I$5:$I$244,'Sample Data'!$D$5:$D$244,$A23,'Sample Data'!$C$5:$C$244,3)/SUMIFS('Sample Data'!$H$5:$H$244,'Sample Data'!$D$5:$D$244,$A23,'Sample Data'!$C$5:$C$244,3),0) -> 0.005203147 | F23: =IFERROR(SUMIFS('Sample Data'!$I$5:$I$244,'Sample Data'!$D$5:$D$244,$A23,'Sample Data'!$C$5:$C$244,4)/SUMIFS('Sample Data'!$H$5:$H$244,'Sample Data'!$D$5:$D$244,$A23,'Sample Data'!$C$5:$C$244,4),0) -> 0.0053584243 | G23: =IFERROR(SUMIFS('Sample Data'!$G$5:$G$244,'Sample Data'!$D$5:$D$244,$A23,'Sample Data'!$C$5:$C$244,1)/SUMIFS('Sample Data'!$H$5:$H$244,'Sample Data'!$D$5:$D$244,$A23,'Sample Data'!$C$5:$C$244,1)*1000,0) -> 24.915052 | H23: =IFERROR(SUMIFS('Sample Data'!$G$5:$G$244,'Sample Data'!$D$5:$D$244,$A23,'Sample Data'!$C$5:$C$244,4)/SUMIFS('Sample Data'!$H$5:$H$244,'Sample Data'!$D$5:$D$244,$A23,'Sample Data'!$C$5:$C$244,4)*1000,0) -> 25.497784 | I23: =IFERROR(SUMIFS('Sample Data'!$L$5:$L$244,'Sample Data'!$D$5:$D$244,$A23,'Sample Data'!$C$5:$C$244,1)/SUMIFS('Sample Data'!$G$5:$G$244,'Sample Data'!$D$5:$D$244,$A23,'Sample Data'!$C$5:$C$244,1),0) -> 0 | J23: =IFERROR(SUMIFS('Sample Data'!$L$5:$L$244,'Sample Data'!$D$5:$D$244,$A23,'Sample Data'!$C$5:$C$244,2)/SUMIFS('Sample Data'!$G$5:$G$244,'Sample Data'!$D$5:$D$244,$A23,'Sample Data'!$C$5:$C$244,2),0) -> 3.0872253 | K23: =IFERROR(SUMIFS('Sample Data'!$L$5:$L$244,'Sample Data'!$D$5:$D$244,$A23,'Sample Data'!$C$5:$C$244,3)/SUMIFS('Sample Data'!$G$5:$G$244,'Sample Data'!$D$5:$D$244,$A23,'Sample Data'!$C$5:$C$244,3),0) -> 0 | L23: =IFERROR(SUMIFS('Sample Data'!$L$5:$L$244,'Sample Data'!$D$5:$D$244,$A23,'Sample Data'!$C$5:$C$244,4)/SUMIFS('Sample Data'!$G$5:$G$244,'Sample Data'!$D$5:$D$244,$A23,'Sample Data'!$C$5:$C$244,4),0) -> 0
A24: =A12 -> C04 | B24: =B12 -> Meta | C24: =IFERROR(SUMIFS('Sample Data'!$I$5:$I$244,'Sample Data'!$D$5:$D$244,$A24,'Sample Data'!$C$5:$C$244,1)/SUMIFS('Sample Data'!$H$5:$H$244,'Sample Data'!$D$5:$D$244,$A24,'Sample Data'!$C$5:$C$244,1),0) -> 0.013468922 | D24: =IFERROR(SUMIFS('Sample Data'!$I$5:$I$244,'Sample Data'!$D$5:$D$244,$A24,'Sample Data'!$C$5:$C$244,2)/SUMIFS('Sample Data'!$H$5:$H$244,'Sample Data'!$D$5:$D$244,$A24,'Sample Data'!$C$5:$C$244,2),0) -> 0.013968845 | E24: =IFERROR(SUMIFS('Sample Data'!$I$5:$I$244,'Sample Data'!$D$5:$D$244,$A24,'Sample Data'!$C$5:$C$244,3)/SUMIFS('Sample Data'!$H$5:$H$244,'Sample Data'!$D$5:$D$244,$A24,'Sample Data'!$C$5:$C$244,3),0) -> 0.0119877 | F24: =IFERROR(SUMIFS('Sample Data'!$I$5:$I$244,'Sample Data'!$D$5:$D$244,$A24,'Sample Data'!$C$5:$C$244,4)/SUMIFS('Sample Data'!$H$5:$H$244,'Sample Data'!$D$5:$D$244,$A24,'Sample Data'!$C$5:$C$244,4),0) -> 0.0089033831 | G24: =IFERROR(SUMIFS('Sample Data'!$G$5:$G$244,'Sample Data'!$D$5:$D$244,$A24,'Sample Data'!$C$5:$C$244,1)/SUMIFS('Sample Data'!$H$5:$H$244,'Sample Data'!$D$5:$D$244,$A24,'Sample Data'!$C$5:$C$244,1)*1000,0) -> 54.652922 | H24: =IFERROR(SUMIFS('Sample Data'!$G$5:$G$244,'Sample Data'!$D$5:$D$244,$A24,'Sample Data'!$C$5:$C$244,4)/SUMIFS('Sample Data'!$H$5:$H$244,'Sample Data'!$D$5:$D$244,$A24,'Sample Data'!$C$5:$C$244,4)*1000,0) -> 64.497815 | I24: =IFERROR(SUMIFS('Sample Data'!$L$5:$L$244,'Sample Data'!$D$5:$D$244,$A24,'Sample Data'!$C$5:$C$244,1)/SUMIFS('Sample Data'!$G$5:$G$244,'Sample Data'!$D$5:$D$244,$A24,'Sample Data'!$C$5:$C$244,1),0) -> 4.3600443 | J24: =IFERROR(SUMIFS('Sample Data'!$L$5:$L$244,'Sample Data'!$D$5:$D$244,$A24,'Sample Data'!$C$5:$C$244,2)/SUMIFS('Sample Data'!$G$5:$G$244,'Sample Data'!$D$5:$D$244,$A24,'Sample Data'!$C$5:$C$244,2),0) -> 4.3208359 | K24: =IFERROR(SUMIFS('Sample Data'!$L$5:$L$244,'Sample Data'!$D$5:$D$244,$A24,'Sample Data'!$C$5:$C$244,3)/SUMIFS('Sample Data'!$G$5:$G$244,'Sample Data'!$D$5:$D$244,$A24,'Sample Data'!$C$5:$C$244,3),0) -> 1.9041234 | L24: =IFERROR(SUMIFS('Sample Data'!$L$5:$L$244,'Sample Data'!$D$5:$D$244,$A24,'Sample Data'!$C$5:$C$244,4)/SUMIFS('Sample Data'!$G$5:$G$244,'Sample Data'!$D$5:$D$244,$A24,'Sample Data'!$C$5:$C$244,4),0) -> 2.2592972
A25: =A13 -> C05 | B25: =B13 -> Google Search | C25: =IFERROR(SUMIFS('Sample Data'!$I$5:$I$244,'Sample Data'!$D$5:$D$244,$A25,'Sample Data'!$C$5:$C$244,1)/SUMIFS('Sample Data'!$H$5:$H$244,'Sample Data'!$D$5:$D$244,$A25,'Sample Data'!$C$5:$C$244,1),0) -> 0.064031667 | D25: =IFERROR(SUMIFS('Sample Data'!$I$5:$I$244,'Sample Data'!$D$5:$D$244,$A25,'Sample Data'!$C$5:$C$244,2)/SUMIFS('Sample Data'!$H$5:$H$244,'Sample Data'!$D$5:$D$244,$A25,'Sample Data'!$C$5:$C$244,2),0) -> 0.064308495 | E25: =IFERROR(SUMIFS('Sample Data'!$I$5:$I$244,'Sample Data'!$D$5:$D$244,$A25,'Sample Data'!$C$5:$C$244,3)/SUMIFS('Sample Data'!$H$5:$H$244,'Sample Data'!$D$5:$D$244,$A25,'Sample Data'!$C$5:$C$244,3),0) -> 0.06029914 | F25: =IFERROR(SUMIFS('Sample Data'!$I$5:$I$244,'Sample Data'!$D$5:$D$244,$A25,'Sample Data'!$C$5:$C$244,4)/SUMIFS('Sample Data'!$H$5:$H$244,'Sample Data'!$D$5:$D$244,$A25,'Sample Data'!$C$5:$C$244,4),0) -> 0.06326238 | G25: =IFERROR(SUMIFS('Sample Data'!$G$5:$G$244,'Sample Data'!$D$5:$D$244,$A25,'Sample Data'!$C$5:$C$244,1)/SUMIFS('Sample Data'!$H$5:$H$244,'Sample Data'!$D$5:$D$244,$A25,'Sample Data'!$C$5:$C$244,1)*1000,0) -> 362.2446 | H25: =IFERROR(SUMIFS('Sample Data'!$G$5:$G$244,'Sample Data'!$D$5:$D$244,$A25,'Sample Data'!$C$5:$C$244,4)/SUMIFS('Sample Data'!$H$5:$H$244,'Sample Data'!$D$5:$D$244,$A25,'Sample Data'!$C$5:$C$244,4)*1000,0) -> 352.97232 | I25: =IFERROR(SUMIFS('Sample Data'!$L$5:$L$244,'Sample Data'!$D$5:$D$244,$A25,'Sample Data'!$C$5:$C$244,1)/SUMIFS('Sample Data'!$G$5:$G$244,'Sample Data'!$D$5:$D$244,$A25,'Sample Data'!$C$5:$C$244,1),0) -> 5.3093363 | J25: =IFERROR(SUMIFS('Sample Data'!$L$5:$L$244,'Sample Data'!$D$5:$D$244,$A25,'Sample Data'!$C$5:$C$244,2)/SUMIFS('Sample Data'!$G$5:$G$244,'Sample Data'!$D$5:$D$244,$A25,'Sample Data'!$C$5:$C$244,2),0) -> 7.8242005 | K25: =IFERROR(SUMIFS('Sample Data'!$L$5:$L$244,'Sample Data'!$D$5:$D$244,$A25,'Sample Data'!$C$5:$C$244,3)/SUMIFS('Sample Data'!$G$5:$G$244,'Sample Data'!$D$5:$D$244,$A25,'Sample Data'!$C$5:$C$244,3),0) -> 8.2420055 | L25: =IFERROR(SUMIFS('Sample Data'!$L$5:$L$244,'Sample Data'!$D$5:$D$244,$A25,'Sample Data'!$C$5:$C$244,4)/SUMIFS('Sample Data'!$G$5:$G$244,'Sample Data'!$D$5:$D$244,$A25,'Sample Data'!$C$5:$C$244,4),0) -> 7.5871766
A26: =A14 -> C06 | B26: =B14 -> Google PMax | C26: =IFERROR(SUMIFS('Sample Data'!$I$5:$I$244,'Sample Data'!$D$5:$D$244,$A26,'Sample Data'!$C$5:$C$244,1)/SUMIFS('Sample Data'!$H$5:$H$244,'Sample Data'!$D$5:$D$244,$A26,'Sample Data'!$C$5:$C$244,1),0) -> 0.014619559 | D26: =IFERROR(SUMIFS('Sample Data'!$I$5:$I$244,'Sample Data'!$D$5:$D$244,$A26,'Sample Data'!$C$5:$C$244,2)/SUMIFS('Sample Data'!$H$5:$H$244,'Sample Data'!$D$5:$D$244,$A26,'Sample Data'!$C$5:$C$244,2),0) -> 0.015481079 | E26: =IFERROR(SUMIFS('Sample Data'!$I$5:$I$244,'Sample Data'!$D$5:$D$244,$A26,'Sample Data'!$C$5:$C$244,3)/SUMIFS('Sample Data'!$H$5:$H$244,'Sample Data'!$D$5:$D$244,$A26,'Sample Data'!$C$5:$C$244,3),0) -> 0.015084644 | F26: =IFERROR(SUMIFS('Sample Data'!$I$5:$I$244,'Sample Data'!$D$5:$D$244,$A26,'Sample Data'!$C$5:$C$244,4)/SUMIFS('Sample Data'!$H$5:$H$244,'Sample Data'!$D$5:$D$244,$A26,'Sample Data'!$C$5:$C$244,4),0) -> 0.014695348 | G26: =IFERROR(SUMIFS('Sample Data'!$G$5:$G$244,'Sample Data'!$D$5:$D$244,$A26,'Sample Data'!$C$5:$C$244,1)/SUMIFS('Sample Data'!$H$5:$H$244,'Sample Data'!$D$5:$D$244,$A26,'Sample Data'!$C$5:$C$244,1)*1000,0) -> 70.938088 | H26: =IFERROR(SUMIFS('Sample Data'!$G$5:$G$244,'Sample Data'!$D$5:$D$244,$A26,'Sample Data'!$C$5:$C$244,4)/SUMIFS('Sample Data'!$H$5:$H$244,'Sample Data'!$D$5:$D$244,$A26,'Sample Data'!$C$5:$C$244,4)*1000,0) -> 68.75918 | I26: =IFERROR(SUMIFS('Sample Data'!$L$5:$L$244,'Sample Data'!$D$5:$D$244,$A26,'Sample Data'!$C$5:$C$244,1)/SUMIFS('Sample Data'!$G$5:$G$244,'Sample Data'!$D$5:$D$244,$A26,'Sample Data'!$C$5:$C$244,1),0) -> 5.5464481 | J26: =IFERROR(SUMIFS('Sample Data'!$L$5:$L$244,'Sample Data'!$D$5:$D$244,$A26,'Sample Data'!$C$5:$C$244,2)/SUMIFS('Sample Data'!$G$5:$G$244,'Sample Data'!$D$5:$D$244,$A26,'Sample Data'!$C$5:$C$244,2),0) -> 2.836767 | K26: =IFERROR(SUMIFS('Sample Data'!$L$5:$L$244,'Sample Data'!$D$5:$D$244,$A26,'Sample Data'!$C$5:$C$244,3)/SUMIFS('Sample Data'!$G$5:$G$244,'Sample Data'!$D$5:$D$244,$A26,'Sample Data'!$C$5:$C$244,3),0) -> 4.7822256 | L26: =IFERROR(SUMIFS('Sample Data'!$L$5:$L$244,'Sample Data'!$D$5:$D$244,$A26,'Sample Data'!$C$5:$C$244,4)/SUMIFS('Sample Data'!$G$5:$G$244,'Sample Data'!$D$5:$D$244,$A26,'Sample Data'!$C$5:$C$244,4),0) -> 3.1853099
A27: =A15 -> C07 | B27: =B15 -> Meta | C27: =IFERROR(SUMIFS('Sample Data'!$I$5:$I$244,'Sample Data'!$D$5:$D$244,$A27,'Sample Data'!$C$5:$C$244,1)/SUMIFS('Sample Data'!$H$5:$H$244,'Sample Data'!$D$5:$D$244,$A27,'Sample Data'!$C$5:$C$244,1),0) -> 0.01773416 | D27: =IFERROR(SUMIFS('Sample Data'!$I$5:$I$244,'Sample Data'!$D$5:$D$244,$A27,'Sample Data'!$C$5:$C$244,2)/SUMIFS('Sample Data'!$H$5:$H$244,'Sample Data'!$D$5:$D$244,$A27,'Sample Data'!$C$5:$C$244,2),0) -> 0.017621059 | E27: =IFERROR(SUMIFS('Sample Data'!$I$5:$I$244,'Sample Data'!$D$5:$D$244,$A27,'Sample Data'!$C$5:$C$244,3)/SUMIFS('Sample Data'!$H$5:$H$244,'Sample Data'!$D$5:$D$244,$A27,'Sample Data'!$C$5:$C$244,3),0) -> 0.017590806 | F27: =IFERROR(SUMIFS('Sample Data'!$I$5:$I$244,'Sample Data'!$D$5:$D$244,$A27,'Sample Data'!$C$5:$C$244,4)/SUMIFS('Sample Data'!$H$5:$H$244,'Sample Data'!$D$5:$D$244,$A27,'Sample Data'!$C$5:$C$244,4),0) -> 0.015310028 | G27: =IFERROR(SUMIFS('Sample Data'!$G$5:$G$244,'Sample Data'!$D$5:$D$244,$A27,'Sample Data'!$C$5:$C$244,1)/SUMIFS('Sample Data'!$H$5:$H$244,'Sample Data'!$D$5:$D$244,$A27,'Sample Data'!$C$5:$C$244,1)*1000,0) -> 84.567264 | H27: =IFERROR(SUMIFS('Sample Data'!$G$5:$G$244,'Sample Data'!$D$5:$D$244,$A27,'Sample Data'!$C$5:$C$244,4)/SUMIFS('Sample Data'!$H$5:$H$244,'Sample Data'!$D$5:$D$244,$A27,'Sample Data'!$C$5:$C$244,4)*1000,0) -> 101.82991 | I27: =IFERROR(SUMIFS('Sample Data'!$L$5:$L$244,'Sample Data'!$D$5:$D$244,$A27,'Sample Data'!$C$5:$C$244,1)/SUMIFS('Sample Data'!$G$5:$G$244,'Sample Data'!$D$5:$D$244,$A27,'Sample Data'!$C$5:$C$244,1),0) -> 3.7936885 | J27: =IFERROR(SUMIFS('Sample Data'!$L$5:$L$244,'Sample Data'!$D$5:$D$244,$A27,'Sample Data'!$C$5:$C$244,2)/SUMIFS('Sample Data'!$G$5:$G$244,'Sample Data'!$D$5:$D$244,$A27,'Sample Data'!$C$5:$C$244,2),0) -> 8.4213477 | K27: =IFERROR(SUMIFS('Sample Data'!$L$5:$L$244,'Sample Data'!$D$5:$D$244,$A27,'Sample Data'!$C$5:$C$244,3)/SUMIFS('Sample Data'!$G$5:$G$244,'Sample Data'!$D$5:$D$244,$A27,'Sample Data'!$C$5:$C$244,3),0) -> 6.0430939 | L27: =IFERROR(SUMIFS('Sample Data'!$L$5:$L$244,'Sample Data'!$D$5:$D$244,$A27,'Sample Data'!$C$5:$C$244,4)/SUMIFS('Sample Data'!$G$5:$G$244,'Sample Data'!$D$5:$D$244,$A27,'Sample Data'!$C$5:$C$244,4),0) -> 3.3577949
A28: =A16 -> C08 | B28: =B16 -> Email + WhatsApp | C28: =IFERROR(SUMIFS('Sample Data'!$I$5:$I$244,'Sample Data'!$D$5:$D$244,$A28,'Sample Data'!$C$5:$C$244,1)/SUMIFS('Sample Data'!$H$5:$H$244,'Sample Data'!$D$5:$D$244,$A28,'Sample Data'!$C$5:$C$244,1),0) -> 0.0817288 | D28: =IFERROR(SUMIFS('Sample Data'!$I$5:$I$244,'Sample Data'!$D$5:$D$244,$A28,'Sample Data'!$C$5:$C$244,2)/SUMIFS('Sample Data'!$H$5:$H$244,'Sample Data'!$D$5:$D$244,$A28,'Sample Data'!$C$5:$C$244,2),0) -> 0.080042463 | E28: =IFERROR(SUMIFS('Sample Data'!$I$5:$I$244,'Sample Data'!$D$5:$D$244,$A28,'Sample Data'!$C$5:$C$244,3)/SUMIFS('Sample Data'!$H$5:$H$244,'Sample Data'!$D$5:$D$244,$A28,'Sample Data'!$C$5:$C$244,3),0) -> 0.075800567 | F28: =IFERROR(SUMIFS('Sample Data'!$I$5:$I$244,'Sample Data'!$D$5:$D$244,$A28,'Sample Data'!$C$5:$C$244,4)/SUMIFS('Sample Data'!$H$5:$H$244,'Sample Data'!$D$5:$D$244,$A28,'Sample Data'!$C$5:$C$244,4),0) -> 0.081085295 | G28: =IFERROR(SUMIFS('Sample Data'!$G$5:$G$244,'Sample Data'!$D$5:$D$244,$A28,'Sample Data'!$C$5:$C$244,1)/SUMIFS('Sample Data'!$H$5:$H$244,'Sample Data'!$D$5:$D$244,$A28,'Sample Data'!$C$5:$C$244,1)*1000,0) -> 618.80377 | H28: =IFERROR(SUMIFS('Sample Data'!$G$5:$G$244,'Sample Data'!$D$5:$D$244,$A28,'Sample Data'!$C$5:$C$244,4)/SUMIFS('Sample Data'!$H$5:$H$244,'Sample Data'!$D$5:$D$244,$A28,'Sample Data'!$C$5:$C$244,4)*1000,0) -> 604.70918 | I28: =IFERROR(SUMIFS('Sample Data'!$L$5:$L$244,'Sample Data'!$D$5:$D$244,$A28,'Sample Data'!$C$5:$C$244,1)/SUMIFS('Sample Data'!$G$5:$G$244,'Sample Data'!$D$5:$D$244,$A28,'Sample Data'!$C$5:$C$244,1),0) -> 5.3889441 | J28: =IFERROR(SUMIFS('Sample Data'!$L$5:$L$244,'Sample Data'!$D$5:$D$244,$A28,'Sample Data'!$C$5:$C$244,2)/SUMIFS('Sample Data'!$G$5:$G$244,'Sample Data'!$D$5:$D$244,$A28,'Sample Data'!$C$5:$C$244,2),0) -> 9.1119558 | K28: =IFERROR(SUMIFS('Sample Data'!$L$5:$L$244,'Sample Data'!$D$5:$D$244,$A28,'Sample Data'!$C$5:$C$244,3)/SUMIFS('Sample Data'!$G$5:$G$244,'Sample Data'!$D$5:$D$244,$A28,'Sample Data'!$C$5:$C$244,3),0) -> 10.767642 | L28: =IFERROR(SUMIFS('Sample Data'!$L$5:$L$244,'Sample Data'!$D$5:$D$244,$A28,'Sample Data'!$C$5:$C$244,4)/SUMIFS('Sample Data'!$G$5:$G$244,'Sample Data'!$D$5:$D$244,$A28,'Sample Data'!$C$5:$C$244,4),0) -> 10.948943

Sheet Optimization
A1: Optimization Decisions & Budget Reallocation
A2: From the Dashboard signals to next month's plan. Recommended shares (blue) are editable; projections update.
A4: 1. Findings
A5: # | B5: Campaign | C5: Signal (live from Dashboard) | D5: Diagnosis | E5: Action next month
A6: 1 | B6: C05 Google Search | C6: ="ROAS "&TEXT(Dashboard!O13,"0.0")&"x vs target "&TEXT(Inputs!$B$10,"0.0")&"x; spent "&TEXT(Dashboard!F13,"0%")&" of plan" -> ROAS 7.3x vs target 3.5x; spent 97% of plan | D6: Strongest closer, capped by budget (daily budget hit every day). | E6: Raise share 22% to 28%. Move to tROAS bidding once 30+ conversions/month.
A7: 2 | B7: C04 Meta prospecting | C7: ="CTR "&TEXT(Dashboard!R12,"0.00%")&" in W1 to "&TEXT(Dashboard!S12,"0.00%")&" in W4 ("&TEXT(Dashboard!T12,"+0%;-0%")&")" -> CTR 1.35% in W1 to 0.89% in W4 (-34%) | D7: Creative fatigue: same 3 Reels shown to a saturated warm pool, CPM rising. | E7: Rotate in new existing catalog cuts and UGC reposts every 10 days; trim share 20% to 17% until CTR recovers.
A8: 3 | B8: C02 YouTube | C8: ="ROAS "&TEXT(Dashboard!O10,"0.00")&"x; position-based share "&TEXT(Dashboard!Q10,"0.0%") -> ROAS 0.88x; position-based share 3.7% | D8: Below break-even and weak as an opener: does not earn its place. | E8: Pause. Move its 5% to Google Search.
A9: 4 | B9: C03 Snapchat | C9: ="ROAS "&TEXT(Dashboard!O11,"0.00")&"x; CVR "&TEXT(Dashboard!M11,"0.00%")&"; assist share "&TEXT(Dashboard!Q11,"0.0%") -> ROAS 0.73x; CVR 0.08%; assist share 3.4% | D9: Clicks are cheap but do not convert: audience skews younger than Mariam. | E9: Pause in Egypt. Re-test only with a 6th of October compound geo-fence.
A10: 5 | B10: C01 TikTok | C10: ="Last-click ROAS "&TEXT(Dashboard!O9,"0.00")&"x but "&TEXT(Dashboard!Q9,"0%")&" of position-based credit" -> Last-click ROAS 0.36x but 20% of position-based credit | D10: Opens the most journeys that later close on Search and Retargeting. | E10: Keep at 15%. Judge on CPM, view rate and assisted conversions, not last-click ROAS.
A11: 6 | B11: C08 Email + WhatsApp | C11: ="ROAS "&TEXT(Dashboard!O16,"0.0")&"x at "&TEXT(Dashboard!D16,"#,##0")&" EGP budget" -> ROAS 9.2x at 12,500 EGP budget | D11: Cheapest revenue in the plan: it fixes the Activation-to-Retention leak. | E11: Double share 5% to 10%: add browse-abandon and room #2 flows.
A12: 7 | B12: C07 Meta retargeting | C12: ="ROAS "&TEXT(Dashboard!O15,"0.0")&"x but CTR "&TEXT(Dashboard!T15,"+0%;-0%")&" W1 to W4 and CPM "&TEXT(Dashboard!H27/Dashboard!G27-1,"+0%;-0%") -> ROAS 5.3x but CTR -14% W1 to W4 and CPM +20% | D12: SCALE signal, but the pool is capped by how many people TOFU/MOFU warm up. More budget here only raises frequency. | E12: Hold at 15%. Cap frequency at 3/week; it grows as TikTok and Meta prospecting feed the pool.
A13: 8 | B13: C06 Google PMax | C13: ="ROAS "&TEXT(Dashboard!O14,"0.0")&"x, above the "&TEXT(Inputs!$B$10,"0.0")&"x target" -> ROAS 4.0x, above the 3.5x target | D13: Profitable feed-only campaign with headroom. | E13: Raise share 13% to 15% with part of the freed YouTube/Snapchat budget.
A15: 2. Budget reallocation for next month
A16: ID | B16: Platform | C16: Current share | D16: Recommended share | E16: Current budget | F16: New budget | G16: Change (EGP) | H16: Actual ROAS (test month) | I16: Revenue at current split | J16: Projected revenue at new split
A17: ='Media Plan'!A5 -> C01 | B17: ='Media Plan'!B5 -> TikTok | C17: ='Media Plan'!I5 -> 0.15 | D17: 0.15 | E17: =C17*Inputs!$B$5 -> 37500 | F17: =D17*Inputs!$B$5 -> 37500 | G17: =F17-E17 -> 0 | H17: =Dashboard!O9 -> 0.36440084 | I17: =H17*E17 -> 13665.032 | J17: =H17*(MIN(F17,E17)+MAX(F17-E17,0)*Inputs!$B$15) -> 13665.032
A18: ='Media Plan'!A6 -> C02 | B18: ='Media Plan'!B6 -> YouTube | C18: ='Media Plan'!I6 -> 0.05 | D18: 0 | E18: =C18*Inputs!$B$5 -> 12500 | F18: =D18*Inputs!$B$5 -> 0 | G18: =F18-E18 -> -12500 | H18: =Dashboard!O10 -> 0.88314358 | I18: =H18*E18 -> 11039.295 | J18: =H18*(MIN(F18,E18)+MAX(F18-E18,0)*Inputs!$B$15) -> 0
A19: ='Media Plan'!A7 -> C03 | B19: ='Media Plan'!B7 -> Snapchat | C19: ='Media Plan'!I7 -> 0.05 | D19: 0 | E19: =C19*Inputs!$B$5 -> 12500 | F19: =D19*Inputs!$B$5 -> 0 | G19: =F19-E19 -> -12500 | H19: =Dashboard!O11 -> 0.72652336 | I19: =H19*E19 -> 9081.5419 | J19: =H19*(MIN(F19,E19)+MAX(F19-E19,0)*Inputs!$B$15) -> 0
A20: ='Media Plan'!A8 -> C04 | B20: ='Media Plan'!B8 -> Meta | C20: ='Media Plan'!I8 -> 0.2 | D20: 0.17 | E20: =C20*Inputs!$B$5 -> 50000 | F20: =D20*Inputs!$B$5 -> 42500 | G20: =F20-E20 -> -7500 | H20: =Dashboard!O12 -> 3.1424606 | I20: =H20*E20 -> 157123.03 | J20: =H20*(MIN(F20,E20)+MAX(F20-E20,0)*Inputs!$B$15) -> 133554.58
A21: ='Media Plan'!A9 -> C05 | B21: ='Media Plan'!B9 -> Google Search | C21: ='Media Plan'!I9 -> 0.22 | D21: 0.28 | E21: =C21*Inputs!$B$5 -> 55000 | F21: =D21*Inputs!$B$5 -> 70000 | G21: =F21-E21 -> 15000 | H21: =Dashboard!O13 -> 7.2637795 | I21: =H21*E21 -> 399507.87 | J21: =H21*(MIN(F21,E21)+MAX(F21-E21,0)*Inputs!$B$15) -> 492121.06
A22: ='Media Plan'!A10 -> C06 | B22: ='Media Plan'!B10 -> Google PMax | C22: ='Media Plan'!I10 -> 0.13 | D22: 0.15 | E22: =C22*Inputs!$B$5 -> 32500 | F22: =D22*Inputs!$B$5 -> 37500 | G22: =F22-E22 -> 5000 | H22: =Dashboard!O14 -> 4.0473934 | I22: =H22*E22 -> 131540.28 | J22: =H22*(MIN(F22,E22)+MAX(F22-E22,0)*Inputs!$B$15) -> 148741.71
A23: ='Media Plan'!A11 -> C07 | B23: ='Media Plan'!B11 -> Meta | C23: ='Media Plan'!I11 -> 0.15 | D23: 0.15 | E23: =C23*Inputs!$B$5 -> 37500 | F23: =D23*Inputs!$B$5 -> 37500 | G23: =F23-E23 -> 0 | H23: =Dashboard!O15 -> 5.288016 | I23: =H23*E23 -> 198300.6 | J23: =H23*(MIN(F23,E23)+MAX(F23-E23,0)*Inputs!$B$15) -> 198300.6
A24: ='Media Plan'!A12 -> C08 | B24: ='Media Plan'!B12 -> Email + WhatsApp | C24: ='Media Plan'!I12 -> 0.05 | D24: 0.1 | E24: =C24*Inputs!$B$5 -> 12500 | F24: =D24*Inputs!$B$5 -> 25000 | G24: =F24-E24 -> 12500 | H24: =Dashboard!O16 -> 9.1660104 | I24: =H24*E24 -> 114575.13 | J24: =H24*(MIN(F24,E24)+MAX(F24-E24,0)*Inputs!$B$15) -> 211963.99
A25: TOTAL | C25: =SUM(C17:C24) -> 1 | D25: =SUM(D17:D24) -> 1 | E25: =SUM(E17:E24) -> 250000 | F25: =SUM(F17:F24) -> 250000 | G25: =SUM(G17:G24) -> 0 | H25: =IFERROR(I25/E25,0) -> 4.1393312 | I25: =SUM(I17:I24) -> 1034832.8 | J25: =SUM(J17:J24) -> 1198347
A27: Blended ROAS at current split | E27: =IFERROR(I25/E25,0) -> 4.1393312
A28: Projected blended ROAS at new split | E28: =IFERROR(J25/F25,0) -> 4.7933879
A29: Projected extra revenue (EGP) | E29: =J25-I25 -> 163514.18
A30: Share check | E30: =IF(ROUND(D25,4)=1,"OK: 100%","CHECK: recommended shares must sum to 100%") -> OK: 100%
A31: Caveat: the projection uses last-click ROAS, so it ignores the assist value lost from paused upper-funnel lines and applies the scaling-efficiency haircut to added budget. Treat it as directional and confirm with a 2-week holdout.
A34: 3. Test backlog (next 30 days)
A35: # | B35: Hypothesis | C35: Test design | D35: Success metric | E35: Min. duration
A36: 1 | B36: If Meta prospecting rotates a fresh asset every 10 days, CTR returns to W1 level and CPM falls. | C36: Ad-set A: current 3 Reels; B: 6 assets rotated every 10 days. 50/50 budget. | D36: CTR, CPM, cost per LPV | E36: 14 days
A37: 2 | B37: tROAS bidding on Google Search lifts ROAS without losing more than 10% of conversions. | C37: Campaign experiment: Max conv. value vs tROAS 450%. 50/50 traffic split. | D37: ROAS, conversions | E37: 21 days
A38: 3 | B38: A delivery-guarantee headline beats a price headline on the bundle landing page. | C38: LP split: 'Delivered on the day we promise' vs 'Full bundle from 4,500 EGP'. | D38: CVR (landing to purchase) | E38: Until 100 conversions per arm
A39: 4 | B39: TikTok drives incremental Search demand. | C39: Geo holdout: pause TikTok in 6th of October for 2 weeks, keep New Cairo live. | D39: Brand search volume, Search conversions by geo | E39: 14 days
